Workbook

Sheet EN articles
A1: ID_ENG | B1: Paper title | C1: Authors | D1: Year | E1: Journal/Conference | F1: Citations | G1: First author | H1: First author affiliation | I1: Author Keywords | J1: MGT/Tech/ENG | K1: Paper type | L1: Methodology | M1: Focus | N1: Application Domain | O1: Use case | P1: industrial sector | Q1: Theory lens | R1: GenAI Technology Type | S1: Key findings | T1: Reported Impacts of GenAI | U1: Enablers / Success Factors | V1: Barriers / Challenges | W1: GenAI role | X1: Tech details | Y1: Comment | Z1: Relevance Rating (1–5) | AA1: Quality Rating (1–5) | AB1: Technology readiness | AC1: Technology readiness - sub level | AD1: GenAI autonomy | AE1: ChatGPT 5.1 Thinking agreement? | AF1: Discrepency | AG1: ChatGPT explanation for Technology readiness (explain) | AH1: ChatGPT explanation for GenAI autonomy (explain) | AI1: My argument | AK1: TRL axis | AL1: GenAI autonomy level
A2: 1 | B2: CausalKGPT: Industrial structure causal knowledge-enhanced large language model for cause analysis of quality problems in aerospace product manufacturing | C2: Zhou B.; Li X.; Liu T.; Xu K.; Liu W.; Bao J. | D2: 2024 | E2: Advanced Engineering Informatics | F2: 61 | G2: =IFERROR(LEFT(C2, FIND(";", C2) - 1), C2) -> Zhou B. | H2: School of Artificial Intelligence, Anhui Polytechnic University, Wuhu, 241000, China | I2: Aerospace product; Causal knowledge graph-guided prompt; Causal quality-related knowledge graph; Cause analysis of quality defects; Large language model | J2: =IF(OR( E2="International Journal of Production Research", E2="Journal of Manufacturing Technology Management", E2="International Journal of Production Economics", E2="Journal of Industrial Information Integration", E2="Transportation Research Part E: Logistics and Transportation Review", E2="Journal of Cleaner Production", E2="MM 2024 - Proceedings of the 32nd ACM International Conference on Multimedia", E2="Oeconomia Copernicana", E2="Technology in Society" ), "MGT", "ENG") -> ENG | K2: empirical | L2: Design science research | M2: Techniques; Applications | N2: Manufacturing | O2: fault diagnosis | P2: Aerospace | R2: KG‑augmented LLM | S2: scgSPN reinforces casual links;CQkg+Ptuned chatglm CausalKgpt beat base+near gpt4 on aerospace qual Q&A | T2: more expert;relaible answers;seclevel responce;enhanced casual robustness for defect diag | U2: highqual CQkg;expert curatd documents | V2: confidental data limits benchmrks;single confounder;need fine grain data;retrianing for reliabilty/safe | X2: scgSPN network modle extracts casual relations from qual docs to build CQkg casual kg;producing CausalKgpt for defect diag | Y2: a KG-enabled fine-tuned LLM on quality issues Q&A in aerospace; data is confidential | Z2: 4 | AA2: 4 | AB2: Lab validation | AC2: Core function validation | AD2: Assistive GenAI | AE2: Y | AG2: Feasibility is shown via comparative experiments in a lab HRC cell (HoloLens2, UR5e+MiR100); results demonstrate performance but not a field pilot/production rollout | AH2: The paper frames CausalKGPT as a tool to assist workers in cause analyses and recommendations and emphasizes an offline model, not one that executes or controls processes. humans remain the decision/actuation gate | AK2: {=_xlfn.IFS(AC2="Principles observation",1, AC2="Concept formulation",2, AC2="Proof-of-concept simulation", 3, AC2="Core function validation", 4, AC2="Integration component testing", 5, AC2="Component validation in relevant environment", 6, AC2="Subsystem demonstration in relevant environment", 7, AC2="System demonstration in operational environment", 8, AC2="Production qualification", 9, AC2="Mission-proven operations", 10)} -> 4 | AL2: {=_xlfn.IFS(AD2="Assistive GenAI", 1, AD2="GenAI-led with human oversight", 2, AD2="Autonomous process learning", 3)} -> 1
A3: 2 | B3: Leveraging error-assisted fine-tuning large language models for manufacturing excellence | C3: Xia L.; Li C.; Zhang C.; Liu S.; Zheng P. | D3: 2024 | E3: Robotics and Computer-Integrated Manufacturing | F3: 45 | G3: =IFERROR(LEFT(C3, FIND(";", C3) - 1), C3) -> Xia L. | H3: Department of Industrial and Systems Engineering, The Hong Kong Polytechnic University, Hong Kong | I3: Generative AI; Industry 4.0; Knowledge management; Large language model; Smart manufacturing | J3: =IF(OR( E3="International Journal of Production Research", E3="Journal of Manufacturing Technology Management", E3="International Journal of Production Economics", E3="Journal of Industrial Information Integration", E3="Transportation Research Part E: Logistics and Transportation Review", E3="Journal of Cleaner Production", E3="MM 2024 - Proceedings of the 32nd ACM International Conference on Multimedia", E3="Oeconomia Copernicana", E3="Technology in Society" ), "MGT", "ENG") -> ENG | K3: empirical | L3: Design science research | M3: Techniques; Applications | N3: Manufacturing | O3: human–robot collaboration | R3: LLM chatbot | S3: mfgtuned llm improve judgment acc~4.1%+gen vaild domian code w/closed loop refinement | T3: better domian answers;more relaible code;eff gains;broader aplicability to mfg tasks | V3: uncertainity;reliabilty;effectiveness;lack domian knowlege | W3: Execute — Translates natural-language tasks and scene context into executable robot code with safety checks and guardrails | X3: errorassisted fine tunning llm w/mfg data;based on openais gpt davinci modle in Python platform | Y3: fine-tuned LLM on robot code generation and more | Z3: 4 | AA3: 4 | AB3: Lab validation | AC3: Core function validation | AD3: Assistive GenAI | AE3: Y | AG3: Proposes and tests a fine-tuning plus error-assisted code generation framework on curated manufacturing corpora and benchmark tasks; code is generated and verified in controlled experiments, not integrated with real shop-floor systems. | AH3: LLM answers manufacturing queries and generates domain-specific code that engineers review, adapt, and deploy; GenAI expands human capability but never directly operates machinery or autonomously executes manufacturing processes. | AK3: {=_xlfn.IFS(AC3="Principles observation",1, AC3="Concept formulation",2, AC3="Proof-of-concept simulation", 3, AC3="Core function validation", 4, AC3="Integration component testing", 5, AC3="Component validation in relevant environment", 6, AC3="Subsystem demonstration in relevant environment", 7, AC3="System demonstration in operational environment", 8, AC3="Production qualification", 9, AC3="Mission-proven operations", 10)} -> 4 | AL3: {=_xlfn.IFS(AD3="Assistive GenAI", 1, AD3="GenAI-led with human oversight", 2, AD3="Autonomous process learning", 3)} -> 1
A4: 3 | B4: From natural language to simulations: applying AI to automate simulation modelling of logistics systems | C4: Jackson I.; Jesus Saenz M.; Ivanov D. | D4: 2024 | E4: International Journal of Production Research | F4: 44 | G4: =IFERROR(LEFT(C4, FIND(";", C4) - 1), C4) -> Jackson I. | H4: Center for Transportation & Logistics, Massachusetts Institute of Technology, Cambridge, MA, United States | I4: artificial intelligence; Generative AI; GPT-3; NLP; simulation; supply chain | J4: ENG | K4: empirical | L4: Design science research | M4: Applications | N4: Supply Chain | O4: modelling of queuing & inventory control | Q4: human-AI collaboration principles | R4: LLM chatbot | S4: codex gen functionaly vaild inventory/queuing simulations from verbal descrips | T4: eff gains | U4: capability of genai;human expert vaild | V4: initial investment;continous updates w/data;scale up;contextulisation of ai | X4: using gpt3 codex davincicodex engine to gen simulaiton modles for inventory+queuing sys | Y4: directly using Codex for code completion for logistics modelling | Z4: 4 | AA4: 4 | AB4: Concept | AC4: Proof-of-concept simulation | AD4: Assistive GenAI | AE4: Y | AG4: GPT-3/Codex is used to automatically generate simulation models from verbal descriptions and validated on queuing and inventory examples entirely in simulation, without connection to real logistics assets or live enterprise data. | AH4: GenAI supports analysts by turning natural language into simulation code; humans still specify problems, inspect generated models, run experiments, and interpret results, so the AI acts as a modelling copilot rather than process controller. | AK4: {=_xlfn.IFS(AC4="Principles observation",1, AC4="Concept formulation",2, AC4="Proof-of-concept simulation", 3, AC4="Core function validation", 4, AC4="Integration component testing", 5, AC4="Component validation in relevant environment", 6, AC4="Subsystem demonstration in relevant environment", 7, AC4="System demonstration in operational environment", 8, AC4="Production qualification", 9, AC4="Mission-proven operations", 10)} -> 3 | AL4: {=_xlfn.IFS(AD4="Assistive GenAI", 1, AD4="GenAI-led with human oversight", 2, AD4="Autonomous process learning", 3)} -> 1
A5: 4 | B5: An LLM-based approach for enabling seamless Human-Robot collaboration in assembly | C5: Gkournelos C.; Konstantinou C.; Makris S., (2) | D5: 2024 | E5: CIRP Annals | F5: 35 | G5: =IFERROR(LEFT(C5, FIND(";", C5) - 1), C5) -> Gkournelos C. | H5: Laboratory for Manufacturing Systems and Automation, Department of Mechanical Engineering and Aeronautics, University of Patras, Patras, Greece | I5: Human robot collaboration; Large language models; Manufacturing systems | J5: =IF(OR( E5="International Journal of Production Research", E5="Journal of Manufacturing Technology Management", E5="International Journal of Production Economics", E5="Journal of Industrial Information Integration", E5="Transportation Research Part E: Logistics and Transportation Review", E5="Journal of Cleaner Production", E5="MM 2024 - Proceedings of the 32nd ACM International Conference on Multimedia", E5="Oeconomia Copernicana", E5="Technology in Society" ), "MGT", "ENG") -> ENG | K5: empirical | L5: Design science research | M5: Applications | N5: Manufacturing | O5: human–robot collaboration; assembly | P5: automotive & machinery | R5: LLM chatbot | S5: llm enabled chatbot rag+CoT prompt engineering based on gpt3.5+gpt4 yields excutable HRC schedules | T5: faster config;improved collabration/eff | X5: rag+CoT prompt engineering based on gpt3.5+gpt4 for 2 assembly tasks in automotive & machinery | Y5: not in-depth tech paper | Z5: 4 | AA5: 2 | AB5: Lab validation | AC5: Integration component testing | AD5: GenAI-led with human oversight | AE5: Y | AG5: Implements an LLM-based execution system integrated with digital twin, knowledge bases, UR10 cobot and AR interface, validated on two assembly testbeds; full stack is exercised, but only in controlled lab-style HRC cells. | AH5: HRC-GPT interprets natural-language requests, generates assembly schedules, allocates tasks and interacts with robot controllers, while operators supervise via AR, can reconfigure and intervene, keeping humans “on the loop” during execution. | AK5: {=_xlfn.IFS(AC5="Principles observation",1, AC5="Concept formulation",2, AC5="Proof-of-concept simulation", 3, AC5="Core function validation", 4, AC5="Integration component testing", 5, AC5="Component validation in relevant environment", 6, AC5="Subsystem demonstration in relevant environment", 7, AC5="System demonstration in operational environment", 8, AC5="Production qualification", 9, AC5="Mission-proven operations", 10)} -> 5 | AL5: {=_xlfn.IFS(AD5="Assistive GenAI", 1, AD5="GenAI-led with human oversight", 2, AD5="Autonomous process learning", 3)} -> 2
A6: 5 | B6: An LLM-based vision and language cobot navigation approach for Human-centric Smart Manufacturing | C6: Wang T.; Fan J.; Zheng P. | D6: 2024 | E6: Journal of Manufacturing Systems | F6: 29 | G6: =IFERROR(LEFT(C6, FIND(";", C6) - 1), C6) -> Wang T. | H6: Department of Industrial and Systems Engineering, The Hong Kong Polytechnic University, Hong Kong | I6: Human-centric smart manufacturing; Large language model; Vision and language navigation | J6: =IF(OR( E6="International Journal of Production Research", E6="Journal of Manufacturing Technology Management", E6="International Journal of Production Economics", E6="Journal of Industrial Information Integration", E6="Transportation Research Part E: Logistics and Transportation Review", E6="Journal of Cleaner Production", E6="MM 2024 - Proceedings of the 32nd ACM International Conference on Multimedia", E6="Oeconomia Copernicana", E6="Technology in Society" ), "MGT", "ENG") -> ENG | K6: empirical | L6: Design science research | M6: Applications | N6: Manufacturing | O6: human–robot collaboration | R6: LLM chatbot | S6: embed llm into Automated Guided Vehicle AGV to comprehend NL commands+gen Python code to;AGV accurately follows complex instructions of toolfetching in humancentric mfg | W6: Execute — Translates natural-language tasks and scene context into executable robot code with safety checks and guardrails | X6: gpt3.5turbo modle from openai employed to convert dialogue+instructions into excutable Python code for impl | Y6: The generated Python code is then executed using the "exec" function in Python to enable the robot to move according to the user's navigation instructions | Z6: 4 | AA6: 3 | AB6: Concept | AC6: Proof-of-concept simulation | AD6: GenAI-led with human oversight | AE6: Y | AG6: Navigation framework is implemented in AI Habitat; a simulated AGV in a reconstructed 3D HRC scene follows language-driven paths. All evaluations occur in simulation, without deployment on physical AGVs or factory IT/OT. | AH6: The LLM interprets human language commands and autonomously generates Python navigation code and paths for the AGV; humans issue goals and could supervise or stop runs, but do not micromanage movement-level actions. | AK6: {=_xlfn.IFS(AC6="Principles observation",1, AC6="Concept formulation",2, AC6="Proof-of-concept simulation", 3, AC6="Core function validation", 4, AC6="Integration component testing", 5, AC6="Component validation in relevant environment", 6, AC6="Subsystem demonstration in relevant environment", 7, AC6="System demonstration in operational environment", 8, AC6="Production qualification", 9, AC6="Mission-proven operations", 10)} -> 3 | AL6: {=_xlfn.IFS(AD6="Assistive GenAI", 1, AD6="GenAI-led with human oversight", 2, AD6="Autonomous process learning", 3)} -> 2
A7: 6 | B7: Empowering digital twins with large language models for global temporal feature learning | C7: Sun Y.; Zhang Q.; Bao J.; Lu Y.; Liu S. | D7: 2024 | E7: Journal of Manufacturing Systems | F7: 26 | G7: =IFERROR(LEFT(C7, FIND(";", C7) - 1), C7) -> Sun Y. | H7: College of Mechanical Engineering, Donghua University, Shanghai, 201620, China | I7: Digital Twin; Large Language Model (LLM); Multi-Agent Systems (MAS) | J7: =IF(OR( E7="International Journal of Production Research", E7="Journal of Manufacturing Technology Management", E7="International Journal of Production Economics", E7="Journal of Industrial Information Integration", E7="Transportation Research Part E: Logistics and Transportation Review", E7="Journal of Cleaner Production", E7="MM 2024 - Proceedings of the 32nd ACM International Conference on Multimedia", E7="Oeconomia Copernicana", E7="Technology in Society" ), "MGT", "ENG") -> ENG | K7: empirical | N7: Operations | O7: fault diagnosis; maintenance | R7: LLM enabled digital twin | S7: genai agents semanticize logs;retrieve cases,+deliberate to recommend causes/prognoses;beat base llms in bridgecrane evaluation | X7: in dt;llm Vicuna13B acts as explainable reasoning engine;recalls similar faults;debates alternatives,+recommends/justifies likely cause+next steps | Y7: low quality paper | Z7: 3 | AA7: 3 | AB7: Concept | AC7: Proof-of-concept simulation | AD7: Assistive GenAI | AE7: Y | AG7: Multi-agent LLM digital twin is evaluated offline on historical crane sensor sequences and fault investigation documents via ablation studies; no real-time coupling or automatic maintenance actions in the actual plant. | AH7: A multi-agent, LLM-driven DT coordinates agents to produce diagnoses/decisions with traceable reasoning; users can intervene, but the system aggregates and fuses insights across agents | AK7: {=_xlfn.IFS(AC7="Principles observation",1, AC7="Concept formulation",2, AC7="Proof-of-concept simulation", 3, AC7="Core function validation", 4, AC7="Integration component testing", 5, AC7="Component validation in relevant environment", 6, AC7="Subsystem demonstration in relevant environment", 7, AC7="System demonstration in operational environment", 8, AC7="Production qualification", 9, AC7="Mission-proven operations", 10)} -> 3 | AL7: {=_xlfn.IFS(AD7="Assistive GenAI", 1, AD7="GenAI-led with human oversight", 2, AD7="Autonomous process learning", 3)} -> 1
A8: 7 | B8: A vision-language-guided and deep reinforcement learning-enabled approach for unstructured human-robot collaborative manufacturing task fulfilment | C8: Zheng P.; Li C.; Fan J.; Wang L. | D8: 2024 | E8: CIRP Annals | F8: 16 | G8: =IFERROR(LEFT(C8, FIND(";", C8) - 1), C8) -> Zheng P. | H8: Department of Industrial and Systems Engineering, The Hong Kong Polytechnic University, Hong Kong | I8: Human-guided robot learning; Human-robot collaboration; Manufacturing system | J8: =IF(OR( E8="International Journal of Production Research", E8="Journal of Manufacturing Technology Management", E8="International Journal of Production Economics", E8="Journal of Industrial Information Integration", E8="Transportation Research Part E: Logistics and Transportation Review", E8="Journal of Cleaner Production", E8="MM 2024 - Proceedings of the 32nd ACM International Conference on Multimedia", E8="Oeconomia Copernicana", E8="Technology in Society" ), "MGT", "ENG") -> ENG | K8: empirical | L8: Design science research | M8: Techniques; Applications | N8: Manufacturing | O8: human–robot collaboration | R8: LLM chatbot | S8: llmbased zeroshot robotic task plan generation;Its feasibility demonstrated in several HRC unstructured mfg tasks | T8: llms for adaptive task planing+Python robot code generation | W8: Execute — Translates natural-language tasks and scene context into executable robot code with safety checks and guardrails | X8: gpt3.5 for robotic task plan generation+codex robot code generation | Y8: another HRC work: commercial LLMs for adaptive task planning and Python robot code generation | Z8: 4 | AA8: 3 | AB8: Lab validation | AC8: Integration component testing | AD8: GenAI-led with human oversight | AE8: Y | AG8: Vision-language planner and DRL controller are implemented on a UR5e+MiR100 mobile manipulator with Kinect and HoloLens in a lab HRC cell; integrated components tested, not deployed on production lines. | AH8: Vision-language + LLM plan tasks and hand off to a DRL controller to execute primitives; human guidance remains central via MR-HMD, so it coordinates modules rather than acting fully autonomously | AK8: {=_xlfn.IFS(AC8="Principles observation",1, AC8="Concept formulation",2, AC8="Proof-of-concept simulation", 3, AC8="Core function validation", 4, AC8="Integration component testing", 5, AC8="Component validation in relevant environment", 6, AC8="Subsystem demonstration in relevant environment", 7, AC8="System demonstration in operational environment", 8, AC8="Production qualification", 9, AC8="Mission-proven operations", 10)} -> 5 | AL8: {=_xlfn.IFS(AD8="Assistive GenAI", 1, AD8="GenAI-led with human oversight", 2, AD8="Autonomous process learning", 3)} -> 2
A9: 8 | B9: Building a knowledge graph to enrich ChatGPT responses in manufacturing service discovery | C9: Li Y.; Starly B. | D9: 2024 | E9: Journal of Industrial Information Integration | F9: 14 | G9: =IFERROR(LEFT(C9, FIND(";", C9) - 1), C9) -> Li Y. | H9: Edward P. Fitts Department of Industrial & Systems Engineering, North Carolina State University, United States | I9: ChatGPT; Digital supply chain; Knowledge graph; Manufacturing service discovery | J9: ENG | K9: empirical | L9: Design science research | M9: Applications | N9: Supply Chain | O9: supplier identification | R9: KG‑augmented LLM | S9: kg+chatgpt beat gpt4 on complex sourcing | T9: more relaible;interpretable QA;efficent manufacturer discovery;supports diversification/resilience | V9: noisy/outdated websites;crossdomian integr;improve llm understanding of kgs | W9: Align — Retrieves and normalizes manufacturer knowledge, translating questions into structured graph queries and answers with provenance. | X9: constructs 13240entity mfg Service kg from websites+Wikidata;Neo4j+LangChain translate NL→Cypher;Node2Vec/GraphSAGE embeddings;chatgpt+kg QA surpasses gpt4 on complex sourcing queries in experiments | Y9: KG+ChatGPT for supplier identification | Z9: 5 | AA9: 4 | AB9: Lab validation | AC9: Core function validation | AD9: Assistive GenAI | AE9: Y | AG9: ChatGPT is integrated with a Neo4j manufacturing knowledge graph built from real company data; evaluation uses offline benchmark questions, with no integration into live procurement workflows or operational IT/OT systems | AH9: System enriches conversational answers about potential manufacturing service providers; it suggests candidates and rationales, but humans still choose suppliers and act, so GenAI only assists information retrieval and decision framing | AK9: {=_xlfn.IFS(AC9="Principles observation",1, AC9="Concept formulation",2, AC9="Proof-of-concept simulation", 3, AC9="Core function validation", 4, AC9="Integration component testing", 5, AC9="Component validation in relevant environment", 6, AC9="Subsystem demonstration in relevant environment", 7, AC9="System demonstration in operational environment", 8, AC9="Production qualification", 9, AC9="Mission-proven operations", 10)} -> 4 | AL9: {=_xlfn.IFS(AD9="Assistive GenAI", 1, AD9="GenAI-led with human oversight", 2, AD9="Autonomous process learning", 3)} -> 1
A10: 9 | B10: A vision-language-guided robotic action planning approach for ambiguity mitigation in human–robot collaborative manufacturing | C10: Fan J.; Zheng P. | D10: 2024 | E10: Journal of Manufacturing Systems | F10: 12 | G10: =IFERROR(LEFT(C10, FIND(";", C10) - 1), C10) -> Fan J. | H10: Department of Industrial and Systems Engineering, The Hong Kong Polytechnic University, Hong Kong | I10: Computer vision; Deep learning; Human–robot collaboration; Smart manufacturing; Vision-language reasoning | J10: =IF(OR( E10="International Journal of Production Research", E10="Journal of Manufacturing Technology Management", E10="International Journal of Production Economics", E10="Journal of Industrial Information Integration", E10="Transportation Research Part E: Logistics and Transportation Review", E10="Journal of Cleaner Production", E10="MM 2024 - Proceedings of the 32nd ACM International Conference on Multimedia", E10="Oeconomia Copernicana", E10="Technology in Society" ), "MGT", "ENG") -> ENG | K10: empirical | L10: Design science research | M10: Techniques; Applications | N10: Manufacturing | O10: human–robot collaboration | R10: LLM chatbot | S10: llm gpt4 robotic planing, 93.3% success | V10: occasional hallucinations | W10: Execute — Translates natural-language tasks and scene context into executable robot code with safety checks and guardrails | X10: llm task planner gpt4/3.5;llama2 generating excutable robot code | Y10: another HRC work: commercial LLMs for adaptive task planning and Python robot code generation | Z10: 4 | AA10: 3 | AB10: Lab validation | AC10: Integration component testing | AD10: GenAI-led with human oversight | AE10: Y | AG10: Referred object retrieval and LLM-based planner are validated on lab HRC gear-pump assembly with UR5 and Kinect plus evaluations on RefCOCO; integrated perception–planning stack tested, not connected to production MES. | AH10: LLM generates executable robot code from language and vision, calling primitive skills to perform pick-and-place; humans provide initial commands and occasional clicks, supervising outcomes but not approving every motion beforehand. | AK10: {=_xlfn.IFS(AC10="Principles observation",1, AC10="Concept formulation",2, AC10="Proof-of-concept simulation", 3, AC10="Core function validation", 4, AC10="Integration component testing", 5, AC10="Component validation in relevant environment", 6, AC10="Subsystem demonstration in relevant environment", 7, AC10="System demonstration in operational environment", 8, AC10="Production qualification", 9, AC10="Mission-proven operations", 10)} -> 5 | AL10: {=_xlfn.IFS(AD10="Assistive GenAI", 1, AD10="GenAI-led with human oversight", 2, AD10="Autonomous process learning", 3)} -> 2
A11: 11 | B11: Generative AI and DT integrated intelligent process planning: a conceptual framework | C11: Xu Q.; Zhou G.; Zhang C.; Chang F.; Cao Y.; Zhao D. | D11: 2024 | E11: International Journal of Advanced Manufacturing Technology | F11: 10 | G11: =IFERROR(LEFT(C11, FIND(";", C11) - 1), C11) -> Xu Q. | H11: School of Mechanical Engineering, Xi’an Jiaotong University, No.28 Xianning West Road, Xi’an, 710049, China | I11: CAPP; DT; Generative AI; Intelligent process planning; Transformer | J11: =IF(OR( E11="International Journal of Production Research", E11="Journal of Manufacturing Technology Management", E11="International Journal of Production Economics", E11="Journal of Industrial Information Integration", E11="Transportation Research Part E: Logistics and Transportation Review", E11="Journal of Cleaner Production", E11="MM 2024 - Proceedings of the 32nd ACM International Conference on Multimedia", E11="Oeconomia Copernicana", E11="Technology in Society" ), "MGT", "ENG") -> ENG | K11: empirical | L11: Design science research | M11: Techniques; Applications | N11: Manufacturing | O11: process planning | R11: LLM enabled digital twin | S11: propose GIPP:Processgpt+dt verfication;finetunes gpt3 on 2458 Q&A;milling prototype show flexibel;veriifiable planing vs CAPP | T11: greater adaptability;userfriendliness;reliabilty;explainability | V11: narrow milling dataset;unimodal gpt3 | W11: Reason — Plans milling processes from textual know-how and revises steps using digital-twin verification feedback for reliability. | X11: fine tunw gpt3 davinci002 Processgpt;it then answers proc questions+drafts proc plans steps;tools;parameters in structured proc card format> Hands plans to dt>dt results loop back to llm for | Y11: proposes conceptual framework-->verify with a prototype. lacking extensive quantitative evaluation | Z11: 4 | AA11: 3 | AB11: Lab validation | AC11: Integration component testing | AD11: GenAI-led with human oversight | AE11: Y | AG11: Prototype GIPP platform couples a fine-tuned ProcessGPT, CAM and a DT of a three-axis CNC milling machine, executing milling of a thin-walled part in an experimental cell, not in full production. | AH11: ProcessGPT automatically proposes complete process plans and drives NC code generation via CAM and DT verification, while engineers supply requirements, review outputs, and supervise machining execution, keeping humans on the loop. | AK11: {=_xlfn.IFS(AC11="Principles observation",1, AC11="Concept formulation",2, AC11="Proof-of-concept simulation", 3, AC11="Core function validation", 4, AC11="Integration component testing", 5, AC11="Component validation in relevant environment", 6, AC11="Subsystem demonstration in relevant environment", 7, AC11="System demonstration in operational environment", 8, AC11="Production qualification", 9, AC11="Mission-proven operations", 10)} -> 5 | AL11: {=_xlfn.IFS(AD11="Assistive GenAI", 1, AD11="GenAI-led with human oversight", 2, AD11="Autonomous process learning", 3)} -> 2
A12: 12 | B12: Assessment of a large language model based digital intelligent assistant in assembly manufacturing | C12: Colabianchi S.; Costantino F.; Sabetta N. | D12: 2024 | E12: Computers in Industry | F12: 10 | G12: =IFERROR(LEFT(C12, FIND(";", C12) - 1), C12) -> Colabianchi S. | H12: Department of computer, control, and management engineering Antonio Ruberti, Sapienza University of Rome, Via Ariosto 25, Rome, 00185, Italy | I12: Artificial intelligence; Chatbot; Experimental design; Industry 4.0; Industry 5.0; Natural language processing | J12: =IF(OR( E12="International Journal of Production Research", E12="Journal of Manufacturing Technology Management", E12="International Journal of Production Economics", E12="Journal of Industrial Information Integration", E12="Transportation Research Part E: Logistics and Transportation Review", E12="Journal of Cleaner Production", E12="MM 2024 - Proceedings of the 32nd ACM International Conference on Multimedia", E12="Oeconomia Copernicana", E12="Technology in Society" ), "MGT", "ENG") -> ENG | K12: empirical | L12: Lab experiment | M12: Applications; Value&Impact | N12: Manufacturing | O12: assembly | R12: LLM chatbot | S12: experimental voice llm assistant for assembly show high answer acc 93%;lower cognitive load+defects 3% hallucinations;strong usability | T12: reduced cognitive load;improved qual;high usability | X12: gpt4Turbo rag chatbot w/voice i/o | Y12: RAG chatbot dev & experiments like in SFS; BUT: participants are students, not workers; in lab instead of industrial context | Z12: 5 | AA12: 5 | AB12: Lab validation | AC12: Core function validation | AD12: Assistive GenAI | AE12: Y | AG12: ChatGPT-based digital intelligent assistant is implemented as a working prototype guiding workers in an assembly workstation with realistic tasks and curated instructions, evaluated experimentally in a controlled lab environment with student operators | AH12: The DIA only delivers instructions, answers questions and suggests actions through natural language; humans still perform all assembly steps, decide responses to issues, and physically operate tools and components. | AK12: {=_xlfn.IFS(AC12="Principles observation",1, AC12="Concept formulation",2, AC12="Proof-of-concept simulation", 3, AC12="Core function validation", 4, AC12="Integration component testing", 5, AC12="Component validation in relevant environment", 6, AC12="Subsystem demonstration in relevant environment", 7, AC12="System demonstration in operational environment", 8, AC12="Production qualification", 9, AC12="Mission-proven operations", 10)} -> 4 | AL12: {=_xlfn.IFS(AD12="Assistive GenAI", 1, AD12="GenAI-led with human oversight", 2, AD12="Autonomous process learning", 3)} -> 1
A13: 13 | B13: A novel approach to voice of customer extraction using GPT-3.5 Turbo: linking advanced NLP and Lean Six Sigma 4.0 | C13: Shahin M.; Chen F.F.; Hosseinzadeh A.; Maghanaki M.; Eghbalian A. | D13: 2024 | E13: International Journal of Advanced Manufacturing Technology | F13: 9 | G13: =IFERROR(LEFT(C13, FIND(";", C13) - 1), C13) -> Shahin M. | H13: Mechanical Engineering Department, The University of Texas at San Antonio, San Antonio, TX, United States | I13: ChatGPT; Industry 4.0; Large language model; Lean Six Sigma; Text mining and analysis; VoC | J13: =IF(OR( E13="International Journal of Production Research", E13="Journal of Manufacturing Technology Management", E13="International Journal of Production Economics", E13="Journal of Industrial Information Integration", E13="Transportation Research Part E: Logistics and Transportation Review", E13="Journal of Cleaner Production", E13="MM 2024 - Proceedings of the 32nd ACM International Conference on Multimedia", E13="Oeconomia Copernicana", E13="Technology in Society" ), "MGT", "ENG") -> ENG | K13: empirical | L13: Design science research | M13: Techniques; Applications | N13: Operations | O13: quality management | Q13: Lean Six Sigma | R13: LLM chatbot | S13: gpt3.5 processes suport dialogues to extract VoC;mapping to needs/requirements;show nuanced | T13: realtime customer insight;improved product/proc decisions;satisfaction;reduced churn | V13: slang/evolving language;historical bias;trend detection limits;ethics | X13: prompt gpt3.5Turbo to map comments→needs→requirements | Y13: simple usecase of chatgpt in extracting VoC, lacks quantitative evaluation | Z13: 4 | AA13: 3 | AB13: Lab validation | AC13: Core function validation | AD13: Assistive GenAI | AE13: Y | AG13: Researchers build a GPT-3.5-Turbo VoC pipeline processing thousands of Apple Support Twitter conversations, validating extraction quality on this real dataset without deploying the system into live customer service operations. | AH13: GPT-3.5-Turbo analyses historical dialogues and returns customer needs and requirements; Lean Six Sigma practitioners then interpret these insights to prioritize improvements, with no automated changes to business or production processes. | AK13: {=_xlfn.IFS(AC13="Principles observation",1, AC13="Concept formulation",2, AC13="Proof-of-concept simulation", 3, AC13="Core function validation", 4, AC13="Integration component testing", 5, AC13="Component validation in relevant environment", 6, AC13="Subsystem demonstration in relevant environment", 7, AC13="System demonstration in operational environment", 8, AC13="Production qualification", 9, AC13="Mission-proven operations", 10)} -> 4 | AL13: {=_xlfn.IFS(AD13="Assistive GenAI", 1, AD13="GenAI-led with human oversight", 2, AD13="Autonomous process learning", 3)} -> 1
A14: 14 | B14: Ontology-integrated tuning of large language model for intelligent maintenance | C14: Wang P.; Karigiannis J.; Gao R.X. | D14: 2024 | E14: CIRP Annals | F14: 8 | G14: =IFERROR(LEFT(C14, FIND(";", C14) - 1), C14) -> Wang P. | H14: Department of Electrical and Computer Engineering, Department of Mechanical and Aerospace Engineering, University of Kentucky, Lexington, KY, United States | I14: Large language models; Machine learning; Maintenance | J14: =IF(OR( E14="International Journal of Production Research", E14="Journal of Manufacturing Technology Management", E14="International Journal of Production Economics", E14="Journal of Industrial Information Integration", E14="Transportation Research Part E: Logistics and Transportation Review", E14="Journal of Cleaner Production", E14="MM 2024 - Proceedings of the 32nd ACM International Conference on Multimedia", E14="Oeconomia Copernicana", E14="Technology in Society" ), "MGT", "ENG") -> ENG | K14: empirical | L14: Design science research | M14: Techniques; Applications | N14: Operations | O14: maintenance | P14: Aerospace | R14: LLM chatbot | S14: ontologytuned gpt3.5 beats base gpt3.5/GP4 on component ID+action recs | T14: more accurate;consistent maint triage | U14: highqual ontology;curated logs | V14: fine tunning API limits;overfitting beyond 1 epoch;dataset repetition;generalizability | X14: encode aircraft ontology in logs;finetune gpt3.5;test on 500 logs;IoU/BERTScore/BLEU metrics | Y14: fine-tuned LLM on aircraft maintenance | Z14: 4 | AA14: 3 | AB14: Lab validation | AC14: Core function validation | AD14: Assistive GenAI | AE14: Y | AG14: GPT-3.5 is fine-tuned with curated aircraft maintenance logs and evaluated using IoU, BERTScore and BLEU, validating defect identification and action recommendation on historical data without integration to operational maintenance systems. | AH14: The fine-tuned LLM interprets free-text maintenance logs and suggests defective components and recommended actions, but humans remain responsible for decision-making and execution; the model neither triggers workflows nor controls equipment. | AI14: aircraft maintenance data is real | AK14: {=_xlfn.IFS(AC14="Principles observation",1, AC14="Concept formulation",2, AC14="Proof-of-concept simulation", 3, AC14="Core function validation", 4, AC14="Integration component testing", 5, AC14="Component validation in relevant environment", 6, AC14="Subsystem demonstration in relevant environment", 7, AC14="System demonstration in operational environment", 8, AC14="Production qualification", 9, AC14="Mission-proven operations", 10)} -> 4 | AL14: {=_xlfn.IFS(AD14="Assistive GenAI", 1, AD14="GenAI-led with human oversight", 2, AD14="Autonomous process learning", 3)} -> 1
A15: 15 | B15: Intelligent smelting process, management system: Efficient and intelligent management strategy by incorporating large language model | C15: Fu T.; Liu S.; Li P. | D15: 2024 | E15: Frontiers of Engineering Management | F15: 7 | G15: =IFERROR(LEFT(C15, FIND(";", C15) - 1), C15) -> Fu T. | H15: The School of Mechanical Engineering, Zhejiang University, Hangzhou, 310058, China | I15: ChatGPT; intelligent Q & A; large language models; process management; smelting steel | J15: =IF(OR( E15="International Journal of Production Research", E15="Journal of Manufacturing Technology Management", E15="International Journal of Production Economics", E15="Journal of Industrial Information Integration", E15="Transportation Research Part E: Logistics and Transportation Review", E15="Journal of Cleaner Production", E15="MM 2024 - Proceedings of the 32nd ACM International Conference on Multimedia", E15="Oeconomia Copernicana", E15="Technology in Society" ), "MGT", "ENG") -> ENG | K15: empirical | L15: Design science research | M15: Techniques; Applications | N15: Manufacturing | O15: anomaly detection | P15: steelmaking | R15: LLM chatbot; VLM | S15: fine tunw chatgpt3.5+clipbased vlm enable defect descrip+QA in smelting proc management | T15: lower management costs;higher eff;better proc comprehension;collaborative ops | U15: modle fine tunning | V15: integr gaps;data qual;need real deployments;reliance on chatgpt3.5 API | X15: chatgpt3.5 llm integrated w/fine tunw Transformer on domianspecific dataset+clipbased vlm | Y15: find tune LLM + VLM for anomaly detection | Z15: 4 | AA15: 3 | AB15: Field pilots | AC15: System demonstration in operational environment | AD15: Assistive GenAI | AE15: N | AF15: Field pilots – Subsystem demonstration in relevant environment | AG15: An integrated VLM+LLM management system connects to real smelting sensors, databases, and UI clients, and is evaluated in a steel plant with production and wastage improvements, indicating subsystem-level field demonstration | AH15: The ChatGPT-based module visualizes and explains smelting data, answers domain questions, and offers decision support. Human operators and managers still interpret advice, adjust parameters, and execute actions; GenAI never directly controls equipment or autonomously schedules production. | AI15: already tested it in a factory and have operational KPIs; and it's a complete system with full data flow, intergreted in a system | AK15: {=_xlfn.IFS(AC15="Principles observation",1, AC15="Concept formulation",2, AC15="Proof-of-concept simulation", 3, AC15="Core function validation", 4, AC15="Integration component testing", 5, AC15="Component validation in relevant environment", 6, AC15="Subsystem demonstration in relevant environment", 7, AC15="System demonstration in operational environment", 8, AC15="Production qualification", 9, AC15="Mission-proven operations", 10)} -> 8 | AL15: {=_xlfn.IFS(AD15="Assistive GenAI", 1, AD15="GenAI-led with human oversight", 2, AD15="Autonomous process learning", 3)} -> 1
A16: 16 | B16: ProcessCarbonAgent: A large language models-empowered autonomous agent for decision-making in manufacturing carbon emission management | C16: Wu T.; Li J.; Bao J.; Liu Q. | D16: 2024 | E16: Journal of Manufacturing Systems | F16: 7 | G16: =IFERROR(LEFT(C16, FIND(";", C16) - 1), C16) -> Wu T. | H16: College of Mechanical Engineering, Donghua University, Shanghai, 201620, China | I16: Assisted decision-making; Autonomous agents; Carbon emission management; Knowledge-intensive production; Large language models; Process carbon agent | J16: =IF(OR( E16="International Journal of Production Research", E16="Journal of Manufacturing Technology Management", E16="International Journal of Production Economics", E16="Journal of Industrial Information Integration", E16="Transportation Research Part E: Logistics and Transportation Review", E16="Journal of Cleaner Production", E16="MM 2024 - Proceedings of the 32nd ACM International Conference on Multimedia", E16="Oeconomia Copernicana", E16="Technology in Society" ), "MGT", "ENG") -> ENG | K16: empirical | L16: Design science research | M16: Techniques; Applications | N16: Manufacturing | O16: fault diagnosis; maintenance | P16: Textile | R16: LLM agents | S16: creates ProcessCarbonAgent:data/intention/CoT agents w/gpt4 controller;improve RCA acc/credibility+speeds carbonmanagement decisions | T16: technical suport for achieving lowcarbon transformation+intelligence in industrial prod processes | W16: Reason — Agents diagnose root causes by interpreting logs, retrieving similar cases, and debating evidence to recommendations. | X16: agent fw:combines data;intention+CoT agents w/gpt4 controller | Y16: agent framework; single-case textile validation | Z16: 4 | AA16: 4 | AB16: Lab validation | AC16: Core function validation | AD16: Assistive GenAI | AE16: Y | AG16: Offline study on historical carbon-emission logs from a textile plant, using semantic text and knowledge graphs, evaluated with automatic metrics and human scores, without deployment, real-time integration, or direct control of production equipment. | AH16: The agent analyzes process logs, retrieves similar cases, and generates textual root-cause explanations and improvement suggestions; engineers and managers interpret recommendations and decide process changes, so GenAI remains a decision-support copilot rather than executing actions. | AK16: {=_xlfn.IFS(AC16="Principles observation",1, AC16="Concept formulation",2, AC16="Proof-of-concept simulation", 3, AC16="Core function validation", 4, AC16="Integration component testing", 5, AC16="Component validation in relevant environment", 6, AC16="Subsystem demonstration in relevant environment", 7, AC16="System demonstration in operational environment", 8, AC16="Production qualification", 9, AC16="Mission-proven operations", 10)} -> 4 | AL16: {=_xlfn.IFS(AD16="Assistive GenAI", 1, AD16="GenAI-led with human oversight", 2, AD16="Autonomous process learning", 3)} -> 1
A17: 17 | B17: Do LLMs Understand Visual Anomalies? Uncovering LLM's Capabilities in Zero-shot Anomaly Detection | C17: Zhu J.; Cai S.; Deng F.; Ooi B.C.; Wu J. | D17: 2024 | E17: MM 2024 - Proceedings of the 32nd ACM International Conference on Multimedia | F17: 5 | G17: =IFERROR(LEFT(C17, FIND(";", C17) - 1), C17) -> Zhu J. | H17: Beijing Institute of Technology, Beijing, China | I17: industrial manufacturing; large vision-language model; visual anomaly detection; zero-shot detection | J17: ENG | K17: empirical | L17: Design science research | M17: Techniques | N17: Manufacturing | O17: anomaly detection | R17: LLM chatbot; VLM | S17: trainingfree ALFA use llmguided prompts+fine grain alignment to detect more defects+pinpoint them | T17: cuts manual prompt engineering;improve zeroshot inspection acc;better pixellevel localization | X17: alfa trainingfree;zeroshot visual anomaly detector combining gpt3.5generated prompts;CLIP visionlanguage features,+fine grain alignment module to score/pixellocalize defects on industrial images w/improved | Y17: training-free LLM + VLM for anomaly detection | Z17: 4 | AA17: 4 | AB17: Lab validation | AC17: Core function validation | AD17: Assistive GenAI | AE17: Y | AG17: Builds an LVLM+LLM pipeline for zero-shot visual anomaly detection and evaluates it on MVTec-AD, VisA and other benchmark datasets, entirely offline, with no integration to manufacturing equipment, sensors, or execution systems | AH17: The system outputs anomaly scores or maps for images; humans or downstream tooling would still decide inspection, repair, or adjustments. The paper targets detection performance, not autonomous closed-loop quality control, routing, or process actuation | AK17: {=_xlfn.IFS(AC17="Principles observation",1, AC17="Concept formulation",2, AC17="Proof-of-concept simulation", 3, AC17="Core function validation", 4, AC17="Integration component testing", 5, AC17="Component validation in relevant environment", 6, AC17="Subsystem demonstration in relevant environment", 7, AC17="System demonstration in operational environment", 8, AC17="Production qualification", 9, AC17="Mission-proven operations", 10)} -> 4 | AL17: {=_xlfn.IFS(AD17="Assistive GenAI", 1, AD17="GenAI-led with human oversight", 2, AD17="Autonomous process learning", 3)} -> 1
A18: 18 | B18: Interoperable information modelling leveraging asset administration shell and large language model for quality control toward zero defect manufacturing | C18: Shi D.; Liedl P.; Bauernhansl T. | D18: 2024 | E18: Journal of Manufacturing Systems | F18: 3 | G18: =IFERROR(LEFT(C18, FIND(";", C18) - 1), C18) -> Shi D. | H18: Fraunhofer Institute for Manufacturing Engineering and Automation IPA, Nobelstraße 12, Stuttgart, 70569, Germany | I18: Asset administration shell; Industry 4.0; Information modelling; Interoperability; Large language model; Ontology; Quality control; Zero defect manufacturing | J18: =IF(OR( E18="International Journal of Production Research", E18="Journal of Manufacturing Technology Management", E18="International Journal of Production Economics", E18="Journal of Industrial Information Integration", E18="Transportation Research Part E: Logistics and Transportation Review", E18="Journal of Cleaner Production", E18="MM 2024 - Proceedings of the 32nd ACM International Conference on Multimedia", E18="Oeconomia Copernicana", E18="Technology in Society" ), "MGT", "ENG") -> ENG | K18: empirical | L18: Design science research | M18: Techniques | N18: Operations | O18: quality management | R18: LLM enabled digital twin | S18: aas asset administration shell+llm automates semantic referencing;cuts manual effort,+improve data interoperability | T18: use of llmbased semantic search function to query information+data within AAS instance for qual | V18: data heterogeneity;fine tunning resorces demands;domian prompts required;singledomian vaild | W18: Align — Maps terms to standards and links datasets, grounding queries for interoperable, findable quality data access. | X18: an llmbased semantic search maps each AAS Submodel Template SMT property name+descrip to correct;An llmChat interface gpt41106preview w/Azure lets users ask NL questions over AAS instances hosted on | Y18: LLM acts as both a semantic mapper (to standards like ECLASS) and a natural-language interface over AAS data | Z18: 4 | AA18: 3 | AB18: Field pilots | AC18: Subsystem demonstration in relevant environment | AD18: Assistive GenAI | AE18: Y | AG18: Implements AAS templates, edge gateways, and LLM-based semantic search on quality data in a real injection-molding line, streaming production measurements into SMT instances and demonstrating subsystem behavior in the operational plant, without closing the control loop. | AH18: The LLM supports semantic search, schema alignment, and interactive querying over AAS instances, helping engineers and data scientists discover quality-relevant information; it neither proposes nor automatically executes process changes, remaining a knowledge and query assistant. | AK18: {=_xlfn.IFS(AC18="Principles observation",1, AC18="Concept formulation",2, AC18="Proof-of-concept simulation", 3, AC18="Core function validation", 4, AC18="Integration component testing", 5, AC18="Component validation in relevant environment", 6, AC18="Subsystem demonstration in relevant environment", 7, AC18="System demonstration in operational environment", 8, AC18="Production qualification", 9, AC18="Mission-proven operations", 10)} -> 7 | AL18: {=_xlfn.IFS(AD18="Assistive GenAI", 1, AD18="GenAI-led with human oversight", 2, AD18="Autonomous process learning", 3)} -> 1
A19: 19 | B19: Brain-like Cognition-Driven Model Factory for IIoT Fault Diagnosis by Combining LLMs With Small Models | C19: Liu Y.; Zhang W.; Bao Z.; Chai X.; Gu M.; Jiang W.; Zhang Z.; Tian Y.; Wang F.-Y. | D19: 2024 | E19: IEEE Internet of Things Journal | F19: 3 | G19: =IFERROR(LEFT(C19, FIND(";", C19) - 1), C19) -> Liu Y. | H19: China University of Petroleum (East China), College of Computer Science and Technology, Qingdao, 266580, China | I19: Brain-like cognition; fault diagnosis; generative vertical federated learning; LLMs; model factory; small models | J19: =IF(OR( E19="International Journal of Production Research", E19="Journal of Manufacturing Technology Management", E19="International Journal of Production Economics", E19="Journal of Industrial Information Integration", E19="Transportation Research Part E: Logistics and Transportation Review", E19="Journal of Cleaner Production", E19="MM 2024 - Proceedings of the 32nd ACM International Conference on Multimedia", E19="Oeconomia Copernicana", E19="Technology in Society" ), "MGT", "ENG") -> ENG | K19: empirical | L19: Design science research | M19: Techniques | N19: Operations | O19: maintenance | R19: LLM chatbot | S19: blcoT llm+GVFL small modles boost diagnostic acc/comprehension+communication eff across five datasets | T19: higher acc;better fault understanding;quicker maint advice | V19: llm domian gaps;heterogeneous features;tuning+privacy | X19: propose modle factory coupling BLCoTguided llm w/hypernetworkgenerated small modles under vertical federated learning;improving IIoT fault diag acc+maint guidance across five datasets | Y19: the LLM is the reasoning and coordination brain: 1. Knowledge-guided reasoning (BLCoT): The LLM is prompted with a brain-like chain-of-thought (BLCoT) template and a fault knowledge graph. 2. Supervisor of a “model factory”: The LLM acts as a supervisor that coordinates many small, specialized models (built via a hypernetwork) 3. Interactive maintenance assistant: The LLM explains the suspected fault in natural language, outlines why, and proposes next diagnostic checks or maintenance steps. | Z19: 4 | AA19: 3 | AB19: Lab validation | AC19: Core function validation | AD19: Assistive GenAI | AE19: Y | AG19: BC-MF is validated on four public IIoT datasets and one proprietary dataset, vertically partitioned for federated learning, with experiments restricted to offline training and evaluation rather than connection to running industrial assets or control systems. | AH19: The LLM supervises feature extraction and reasoning, then returns fault labels and maintenance recommendations, while small models perform precise diagnosis; technicians still decide and implement actions, so the framework augments analysis rather than autonomously operating equipment. | AK19: {=_xlfn.IFS(AC19="Principles observation",1, AC19="Concept formulation",2, AC19="Proof-of-concept simulation", 3, AC19="Core function validation", 4, AC19="Integration component testing", 5, AC19="Component validation in relevant environment", 6, AC19="Subsystem demonstration in relevant environment", 7, AC19="System demonstration in operational environment", 8, AC19="Production qualification", 9, AC19="Mission-proven operations", 10)} -> 4 | AL19: {=_xlfn.IFS(AD19="Assistive GenAI", 1, AD19="GenAI-led with human oversight", 2, AD19="Autonomous process learning", 3)} -> 1
A20: 21 | B20: Enhancing Quality Control: A Study on AI and Human Performance in Flip Chip Defect Detection | C20: Cheamsiri W.; Jitpattanakul A.; Muneesawang P.; Wongpatikaseree K.; Hnoohom N. | D20: 2024 | E20: IEEE Access | F20: 1 | G20: =IFERROR(LEFT(C20, FIND(";", C20) - 1), C20) -> Cheamsiri W. | H20: Faculty of Engineering, Mahidol University, Image Information and Intelligence Laboratory, Department of Computer Engineering, Nakhon Pathom, 73170, Thailand | I20: cross section; deep learning; Flip chip defect; generative artificial intelligence; object detection; YOLO models | J20: =IF(OR( E20="International Journal of Production Research", E20="Journal of Manufacturing Technology Management", E20="International Journal of Production Economics", E20="Journal of Industrial Information Integration", E20="Transportation Research Part E: Logistics and Transportation Review", E20="Journal of Cleaner Production", E20="MM 2024 - Proceedings of the 32nd ACM International Conference on Multimedia", E20="Oeconomia Copernicana", E20="Technology in Society" ), "MGT", "ENG") -> ENG | K20: empirical | L20: Design science research | M20: Techniques; Applications | N20: Manufacturing | O20: anomaly detection | P20: Semiconductor | R20: data augmentation | S20: generative augmentation improve minorityclass recall | T20: highmagnification imaging;classbalanced datasets | V20: hip scarcity | W20: Align — Generates scarce defect examples and balances classes to improve training recall and robustness during inspection | X20: getimg.ai gen synthetic HIP images from existing ones to enhance dataset+address HIP image imbalance | Y20: genAI for image data augmentation | Z20: 3 | AA20: 3 | AB20: Lab validation | AC20: Core function validation | AD20: Assistive GenAI | AE20: Y | AG20: Prototype defect-detection models trained with real microscope images from an EMS provider, augmented using generative AI. Evaluation is offline on curated datasets, with no integration into inline inspection equipment or factory IT systems. | AH20: Generative model only synthesizes images for training, while the defect detector provides classification results for inspectors or future systems; no autonomous process control, routing, or closed-loop adjustments are executed. | AK20: {=_xlfn.IFS(AC20="Principles observation",1, AC20="Concept formulation",2, AC20="Proof-of-concept simulation", 3, AC20="Core function validation", 4, AC20="Integration component testing", 5, AC20="Component validation in relevant environment", 6, AC20="Subsystem demonstration in relevant environment", 7, AC20="System demonstration in operational environment", 8, AC20="Production qualification", 9, AC20="Mission-proven operations", 10)} -> 4 | AL20: {=_xlfn.IFS(AD20="Assistive GenAI", 1, AD20="GenAI-led with human oversight", 2, AD20="Autonomous process learning", 3)} -> 1
A21: 22 | B21: Revolutionizing glass molding process: ChatGPT’s role in repairing and recycling lenses | C21: Cao S.; Lim W.H.; Zhu Y.J.; Li T.Y.; Liu Z.H.; Sheng H.Y. | D21: 2024 | E21: International Journal of Advanced Manufacturing Technology | F21: 0 | G21: =IFERROR(LEFT(C21, FIND(";", C21) - 1), C21) -> Cao S. | H21: Faculty of Engineering, Technology and Built Environment, UCSI University, Kuala Lumpur, 56000, Malaysia | I21: ChatGPT; CO<sub>2</sub> emissions; Energy consumption; Glass molding process; Recycling plans | J21: =IF(OR( E21="International Journal of Production Research", E21="Journal of Manufacturing Technology Management", E21="International Journal of Production Economics", E21="Journal of Industrial Information Integration", E21="Transportation Research Part E: Logistics and Transportation Review", E21="Journal of Cleaner Production", E21="MM 2024 - Proceedings of the 32nd ACM International Conference on Multimedia", E21="Oeconomia Copernicana", E21="Technology in Society" ), "MGT", "ENG") -> ENG | K21: empirical | L21: Design science research | M21: Applications | N21: Manufacturing | O21: re-manufacturing | R21: LLM chatbot | S21: chatgpt provides feasible plans for Repair/recycle substandard molded lenses | T21: faster option generation | V21: not always optimal;need vaild;impl complexity for some plans;domian expertise needed | X21: use chatgpt to propose+experimentally validate lens recycling plans | Y21: using ChatGPT to design recycling/repair plans for glass molding process lenses. ChatGPT proposes six recycling plans; lab experiments evaluate quality, economics, and green performance. | Z21: 4 | AA21: 2 | AB21: Lab validation | AC21: Core function validation | AD21: Assistive GenAI | AE21: Y | AG21: ChatGPT is used to propose modified repair and recycling process routes, then recipes are experimentally tested on lab-scale glass molding and annealing equipment with real lenses, showing technical feasibility but no production-line integration. | AH21: ChatGPT suggests process parameters, repair strategies, and troubleshooting ideas in natural language; human experts filter responses, design experiments, set machine parameters, and run trials, so GenAI informs decisions without directly executing or supervising manufacturing operations. | AK21: {=_xlfn.IFS(AC21="Principles observation",1, AC21="Concept formulation",2, AC21="Proof-of-concept simulation", 3, AC21="Core function validation", 4, AC21="Integration component testing", 5, AC21="Component validation in relevant environment", 6, AC21="Subsystem demonstration in relevant environment", 7, AC21="System demonstration in operational environment", 8, AC21="Production qualification", 9, AC21="Mission-proven operations", 10)} -> 4 | AL21: {=_xlfn.IFS(AD21="Assistive GenAI", 1, AD21="GenAI-led with human oversight", 2, AD21="Autonomous process learning", 3)} -> 1
A22: 23 | B22: SHIELD: LLM-Driven Schema Induction for Predictive Analytics in EV Battery Supply Chain Disruptions | C22: Cheng Z.-Q.; Dong Y.; Shi A.; Liu W.; Hu Y.; O’Connor J.; Hauptmann A.G.; Whitefoot K.S. | D22: 2024 | E22: EMNLP 2024 - 2024 Conference on Empirical Methods in Natural Language Processing, Proceedings of the Industry Track | F22: 0 | G22: =IFERROR(LEFT(C22, FIND(";", C22) - 1), C22) -> Cheng Z.-Q. | H22: Carnegie Mellon University, United States | J22: =IF(OR( E22="International Journal of Production Research", E22="Journal of Manufacturing Technology Management", E22="International Journal of Production Economics", E22="Journal of Industrial Information Integration", E22="Transportation Research Part E: Logistics and Transportation Review", E22="Journal of Cleaner Production", E22="MM 2024 - Proceedings of the 32nd ACM International Conference on Multimedia", E22="Oeconomia Copernicana", E22="Technology in Society" ), "MGT", "ENG") -> ENG | K22: empirical | L22: Design science research | M22: Applications | N22: Supply Chain | O22: disruption prediction | P22: automotive | R22: LLM chatbot | S22: llms gpt4o;Llama3 for schema;fine tunw roberta;GCNs w/logical constaints | X22: llms first draft disruption schemas;event+actor templates w/slots;reviewed by experts;Then they propose schema matches for each news paragraph | Y22: LLM-driven schema learning to construct a comprehensive knowledge library | Z22: 4 | AA22: 4 | AB22: Lab validation | AC22: Core function validation | AD22: Assistive GenAI | AE22: Y | AG22: SHIELD implements an LLM-based pipeline that induces schemas and features from EV battery disruption texts and evaluates predictive performance on historical corpora, but remains a research prototype without deployment into operational supply-chain planning systems. | AH22: The LLM structures data, generates features, and produces explanations that support analysts’ predictive models; humans interpret results and decide mitigation actions, so GenAI enhances analytics but does not autonomously trigger supply-chain interventions. | AK22: {=_xlfn.IFS(AC22="Principles observation",1, AC22="Concept formulation",2, AC22="Proof-of-concept simulation", 3, AC22="Core function validation", 4, AC22="Integration component testing", 5, AC22="Component validation in relevant environment", 6, AC22="Subsystem demonstration in relevant environment", 7, AC22="System demonstration in operational environment", 8, AC22="Production qualification", 9, AC22="Mission-proven operations", 10)} -> 4 | AL22: {=_xlfn.IFS(AD22="Assistive GenAI", 1, AD22="GenAI-led with human oversight", 2, AD22="Autonomous process learning", 3)} -> 1
A23: 24 | B23: Foundation models assist in human–robot collaboration assembly | C23: Ji Y.; Zhang Z.; Tang D.; Zheng Y.; Liu C.; Zhao Z.; Li X. | D23: 2024 | E23: Scientific Reports | F23: 0 | G23: =IFERROR(LEFT(C23, FIND(";", C23) - 1), C23) -> Ji Y. | H23: College of Mechanical and Electrical Engineering, Nanjing University of Aeronautics and Astronautics, Nanjing, 210016, China | I23: Foundation models; Human–robot collaboration; Intelligent manufacture; Large language models; Vision foundation models | J23: =IF(OR( E23="International Journal of Production Research", E23="Journal of Manufacturing Technology Management", E23="International Journal of Production Economics", E23="Journal of Industrial Information Integration", E23="Transportation Research Part E: Logistics and Transportation Review", E23="Journal of Cleaner Production", E23="MM 2024 - Proceedings of the 32nd ACM International Conference on Multimedia", E23="Oeconomia Copernicana", E23="Technology in Society" ), "MGT", "ENG") -> ENG | K23: empirical | L23: Design science research | M23: Techniques; Applications | N23: Manufacturing | O23: human–robot collaboration; assembly | R23: LLM chatbot | S23: the llm reads your instruction+scene;then writes robots stepbystep commands;assemblyfocused prompt lets it handle new tasks;not just preset routines | T23: llm planing adds generalization to unseen tasks+NL programmability | V23: responce speed | W23: Execute — Translates natural-language tasks and scene context into executable robot code with safety checks and guardrails | X23: gpt3.5turbo+gpt40613 w/API for task reasoning w/HRC prompts | Y23: the LLM translates text + scene context into robot code | Z23: 4 | AA23: 4 | AB23: Lab validation | AC23: Integration component testing | AD23: GenAI-led with human oversight | AE23: Y | AG23: The system couples vision and language foundation models with a real cobot, cameras, AR/VR interfaces, and controllers in a lab assembly cell, validating perception, planning, and robot execution interactions, not yet on industrial lines. | AH23: Foundation models interpret natural-language instructions, plan actions, and drive robot motion for collaborative assembly, while humans specify tasks, supervise execution, and can intervene, so GenAI leads task execution but under explicit human oversight. | AK23: {=_xlfn.IFS(AC23="Principles observation",1, AC23="Concept formulation",2, AC23="Proof-of-concept simulation", 3, AC23="Core function validation", 4, AC23="Integration component testing", 5, AC23="Component validation in relevant environment", 6, AC23="Subsystem demonstration in relevant environment", 7, AC23="System demonstration in operational environment", 8, AC23="Production qualification", 9, AC23="Mission-proven operations", 10)} -> 5 | AL23: {=_xlfn.IFS(AD23="Assistive GenAI", 1, AD23="GenAI-led with human oversight", 2, AD23="Autonomous process learning", 3)} -> 2
A24: 25 | B24: From concept to manufacturing: evaluating vision-language models for engineering design | C24: Picard C.; Edwards K.M.; Doris A.C.; Man B.; Giannone G.; Alam M.F.; Ahmed F. | D24: 2025 | E24: Artificial Intelligence Review | F24: 55 | G24: =IFERROR(LEFT(C24, FIND(";", C24) - 1), C24) -> Picard C. | H24: Department of Mechanical Engineering, Massachusetts Institute of Technology, Cambridge, 02139, MA, United States | J24: =IF(OR( E24="International Journal of Production Research", E24="Journal of Manufacturing Technology Management", E24="International Journal of Production Economics", E24="Journal of Industrial Information Integration", E24="Transportation Research Part E: Logistics and Transportation Review", E24="Journal of Cleaner Production", E24="MM 2024 - Proceedings of the 32nd ACM International Conference on Multimedia", E24="Oeconomia Copernicana", E24="Technology in Society" ), "MGT", "ENG") -> ENG | K24: empirical | L24: Controlled benchmarks | M24: Applications | N24: Design | O24: Manufacturability assessment; Defect identification | R24: VLM | S24: conceptual design:vlms can compare sketches;write helpful descrips,+suggest selection criteria;best when given text context;syslevel & detailed design:they read basic drawings+draft or review simple CAD code | T24: conceptual design:Speeds early idea screening;reduce repetitive sketch comparisons,+autowrites useful descrips;syslevel & detailed design:Helps read drawings+draft simple CAD;accelerating feedback loops+crossdiscipline communication w/human oversight | V24: conceptual design:Sensitive to sketch qual+missing text context;may misread hand drawings or embedded text;similarity judgments vary w/prompts;can invent criteria or overlook key ones | W24: Conceptual design — Roles: Enhance & Decide 15 words: Structures sketches and descriptions, then judges similarity and suggests selection criteria for screening early concepts. System-level & detailed design — Roles: Enhance & Decide 15 words: Parses drawings and constraints, drafts simple CAD code, and weighs options to support detailed decisions. Manufacturing & inspection — Roles: Enhance & Decide 15 words: Aggregates manufacturing rules, highlights manufacturability risks, and flags obvious defects for first-pass checks before review. | X24: gpt4v;LLaVA1.6 34B | Y24: evaluation of VLM on different design/inspection tasks | Z24: 5 | AA24: 5 | AB24: Lab validation | AC24: Core function validation | AD24: Assistive GenAI | AE24: Y | AG24: GPT-4V/LLaVA are benchmarked on curated, realistic engineering and manufacturing tasks (design similarity, DfM, inspection, CAD, topology optimization). Experiments validate capabilities offline, without integrated workflow, live systems, or deployment. | AH24: Models act purely as analysis and ideation copilots—describing sketches, suggesting materials, judging manufacturability, solving textbook problems. Humans initiate queries, interpret results, and make all decisions; no automated control, execution, or closed-loop process learning. | AK24: {=_xlfn.IFS(AC24="Principles observation",1, AC24="Concept formulation",2, AC24="Proof-of-concept simulation", 3, AC24="Core function validation", 4, AC24="Integration component testing", 5, AC24="Component validation in relevant environment", 6, AC24="Subsystem demonstration in relevant environment", 7, AC24="System demonstration in operational environment", 8, AC24="Production qualification", 9, AC24="Mission-proven operations", 10)} -> 4 | AL24: {=_xlfn.IFS(AD24="Assistive GenAI", 1, AD24="GenAI-led with human oversight", 2, AD24="Autonomous process learning", 3)} -> 1
A25: 26 | B25: Embodied intelligence in manufacturing: leveraging large language models for autonomous industrial robotics | C25: Fan H.; Liu X.; Fuh J.Y.H.; Lu W.F.; Li B. | D25: 2025 | E25: Journal of Intelligent Manufacturing | F25: 29 | G25: =IFERROR(LEFT(C25, FIND(";", C25) - 1), C25) -> Fan H. | H25: Department of Mechanical Engineering, National University of Singapore, 9 Engineering Drive 1, Singapore | I25: Autonomous design; Decision-making; Embodied intelligence; Industrial robotics; Large language models (LLMs) agents | J25: =IF(OR( E25="International Journal of Production Research", E25="Journal of Manufacturing Technology Management", E25="International Journal of Production Economics", E25="Journal of Industrial Information Integration", E25="Transportation Research Part E: Logistics and Transportation Review", E25="Journal of Cleaner Production", E25="MM 2024 - Proceedings of the 32nd ACM International Conference on Multimedia", E25="Oeconomia Copernicana", E25="Technology in Society" ), "MGT", "ENG") -> ENG | K25: empirical | L25: Design science research | M25: Techniques; Applications | N25: Manufacturing | O25: human–robot collaboration | R25: LLM chatbot | S25: the propose llmagent architecture;its genai contribution modular;agentic planing/execution fw w/memory;error handling,+reflection | T25: genai reduce programming effort+improve planing acc+autonomy in multistep mfg tasks compared w/ | U25: deploying genai need welldefined robot/APIs+scene modles URDF;incontext memory;error/exception handling+reflection modules;interpolation libraries,+human review to approve excutable plans | V25: firms face spatial reasoning limits for 3D toolpaths;Gcode complexity;planing latency,+need for visual grounding+realtime feedback loops | W25: Execute — Translates natural-language tasks into robot code/toolpaths, orchestrating APIs and checks for safe execution | X25: compared gpt3.5;gpt4,+LLaMa2 family modles | Y25: LLMs for autonomous industrial robotics planning and execution | Z25: 4 | AA25: 4 | AB25: Concept | AC25: Proof-of-concept simulation | AD25: GenAI-led with human oversight | AE25: Y | AG25: Proposes and implements LLM-controlled robot agents only in physics simulation (PyBullet), with no connection to real hardware or live production systems, reporting task success metrics on synthetic scenarios. | AH25: LLM agent parses natural-language tasks, plans motions and generates robot code executed automatically in simulation, while humans define goals and evaluate results rather than approving every individual action. | AK25: {=_xlfn.IFS(AC25="Principles observation",1, AC25="Concept formulation",2, AC25="Proof-of-concept simulation", 3, AC25="Core function validation", 4, AC25="Integration component testing", 5, AC25="Component validation in relevant environment", 6, AC25="Subsystem demonstration in relevant environment", 7, AC25="System demonstration in operational environment", 8, AC25="Production qualification", 9, AC25="Mission-proven operations", 10)} -> 3 | AL25: {=_xlfn.IFS(AD25="Assistive GenAI", 1, AD25="GenAI-led with human oversight", 2, AD25="Autonomous process learning", 3)} -> 2
A26: 27 | B26: An advanced retrieval-augmented generation system for manufacturing quality control | C26: Heredia Álvaro J.A.; Barreda J.G. | D26: 2025 | E26: Advanced Engineering Informatics | F26: 6 | G26: =IFERROR(LEFT(C26, FIND(";", C26) - 1), C26) -> Heredia Álvaro J.A. | H26: Industry 4.0 Chair, Universitat Jaume I, Castellón, Spain | I26: Ceramic tile; Knowledge-based systems; Large language models; Quality control; Retrieval-augmented generation | J26: =IF(OR( E26="International Journal of Production Research", E26="Journal of Manufacturing Technology Management", E26="International Journal of Production Economics", E26="Journal of Industrial Information Integration", E26="Transportation Research Part E: Logistics and Transportation Review", E26="Journal of Cleaner Production", E26="MM 2024 - Proceedings of the 32nd ACM International Conference on Multimedia", E26="Oeconomia Copernicana", E26="Technology in Society" ), "MGT", "ENG") -> ENG | K26: empirical | L26: Design science research | M26: Techniques; Applications | N26: Manufacturing | O26: quality management | P26: Ceramic-tile | R26: LLM chatbot | S26: the rag sys;combining gpt3.5 w/ceramicdefect corpus external manuals & academic papers;achieves 92.7 % Jaccard+0.61 ROUGEL;far outperforming gpt4 w/o domian grounding | T26: genai delivers faster;more relaible answers for qual troubleshooting;cutting manual search time+reducing scrap | U26: successful deployment relies on wellcurated domian corpus;vector database indexing;LangChain rag pipeline;lowcost API access,+expert review of retrieval rules | V26: effectiveness depends on corpus qual;externalserver latency+residual hallucinations need monitoring+periodic knowlegebase updates | W26: Align — Integrates domain corpus with GPT-3.5 via RAG to ground answers for quality control | X26: rag based on gpt3.5turboinstruct modle | Y26: Future work could explore its implementation in other industries, where the integration of external knowledge bases with internal operational data could further enhance its performance. | Z26: 4 | AA26: 5 | AB26: Lab validation | AC26: Core function validation | AD26: Assistive GenAI | AE26: Y | AG26: Implements a domain-specific RAG assistant using GPT-3.5 with curated ceramic-defect literature, evaluated on retrieval and generation metrics and use-case scenarios, but not integrated with live plant systems or operational data streams. | AH26: Assistant retrieves defect knowledge and drafts explanations or corrective actions for quality engineers, but never triggers inspections or process changes itself, leaving humans as ultimate decision-makers and executors. | AK26: {=_xlfn.IFS(AC26="Principles observation",1, AC26="Concept formulation",2, AC26="Proof-of-concept simulation", 3, AC26="Core function validation", 4, AC26="Integration component testing", 5, AC26="Component validation in relevant environment", 6, AC26="Subsystem demonstration in relevant environment", 7, AC26="System demonstration in operational environment", 8, AC26="Production qualification", 9, AC26="Mission-proven operations", 10)} -> 4 | AL26: {=_xlfn.IFS(AD26="Assistive GenAI", 1, AD26="GenAI-led with human oversight", 2, AD26="Autonomous process learning", 3)} -> 1
A27: 28 | B27: Knowledge extraction for additive manufacturing process via named entity recognition with LLMs | C27: Liu X.; Erkoyuncu J.A.; Fuh J.Y.H.; Lu W.F.; Li B. | D27: 2025 | E27: Robotics and Computer-Integrated Manufacturing | F27: 6 | G27: =IFERROR(LEFT(C27, FIND(";", C27) - 1), C27) -> Liu X. | H27: Department of Mechanical Engineering, National University of Singapore, 9 Engineering Drive 1, Singapore | I27: Additive manufacturing; Domain knowledge management; Fused deposition modeling; Large Language Models; Named entity recognition; Retrieval augmented generation | J27: =IF(OR( E27="International Journal of Production Research", E27="Journal of Manufacturing Technology Management", E27="International Journal of Production Economics", E27="Journal of Industrial Information Integration", E27="Transportation Research Part E: Logistics and Transportation Review", E27="Journal of Cleaner Production", E27="MM 2024 - Proceedings of the 32nd ACM International Conference on Multimedia", E27="Oeconomia Copernicana", E27="Technology in Society" ), "MGT", "ENG") -> ENG | K27: empirical | L27: Design science research | M27: Techniques; Applications | N27: Manufacturing | O27: additive manufacturing | R27: LLM chatbot | S27: the creates integrated FDM taxonomy+show claude3opus+ICL achieves F1 0.915;evidencing genais superiority for lowresorces;proclevel NER | T27: genai sharply boosts entityextraction acc;enabling faster;richer capture of additivemfg knowlege for design;troubleshooting+training | U27: successful deployment depends on curated FDM corpus;integrated taxonomy;promptengineered ICL;limitd fine tunning data,+selecting advanced llms gpt4 | V27: limitd labelled data;API cost/latency;domiancoverage gaps for nonFDM processes,+dependence on continual taxonomy updates hinder widespread industrial rollout | W27: Align — Uses GPT-4/Claude-3 to map text entities to a structured FDM taxonomy, grounding knowledge | X27: use gpt4/claude3 to map text entities to structured FDM taxonomy | Y27: for knowledge extraction; still a lab study, needs real factory logs and broader AM processes | Z27: 4 | AA27: 4 | AB27: Lab validation | AC27: Core function validation | AD27: Assistive GenAI | AE27: Y | AG27: Develops and evaluates an LLM-based NER pipeline on curated additive-manufacturing literature and generated texts, with annotated datasets and offline metrics, without any integration into shop-floor systems or real-time production workflows. | AH27: System automatically extracts process entities and relations from documents to support knowledge structuring and future decision tools, but outputs remain analytical annotations, requiring humans or downstream systems to interpret and act. | AK27: {=_xlfn.IFS(AC27="Principles observation",1, AC27="Concept formulation",2, AC27="Proof-of-concept simulation", 3, AC27="Core function validation", 4, AC27="Integration component testing", 5, AC27="Component validation in relevant environment", 6, AC27="Subsystem demonstration in relevant environment", 7, AC27="System demonstration in operational environment", 8, AC27="Production qualification", 9, AC27="Mission-proven operations", 10)} -> 4 | AL27: {=_xlfn.IFS(AD27="Assistive GenAI", 1, AD27="GenAI-led with human oversight", 2, AD27="Autonomous process learning", 3)} -> 1
A28: 29 | B28: Dual data mapping with fine-tuned large language models and asset administration shells toward interoperable knowledge representation | C28: Shi D.; Meyer O.; Oberle M.; Bauernhansl T. | D28: 2025 | E28: Robotics and Computer-Integrated Manufacturing | F28: 5 | G28: =IFERROR(LEFT(C28, FIND(";", C28) - 1), C28) -> Shi D. | H28: Fraunhofer Institute for Manufacturing Engineering and Automation IPA, Nobelstraße 12, Stuttgart, 70569, Germany | I28: Asset administration shell; Digital twin; Entity matching; Interoperability; Knowledge representation; Large language model | J28: =IF(OR( E28="International Journal of Production Research", E28="Journal of Manufacturing Technology Management", E28="International Journal of Production Economics", E28="Journal of Industrial Information Integration", E28="Transportation Research Part E: Logistics and Transportation Review", E28="Journal of Cleaner Production", E28="MM 2024 - Proceedings of the 32nd ACM International Conference on Multimedia", E28="Oeconomia Copernicana", E28="Technology in Society" ), "MGT", "ENG") -> ENG | K28: empirical | L28: Design science research | M28: Techniques; Applications | N28: Manufacturing | O28: process monitoring | P28: Machinery | R28: LLM enabled digital twin | S28: the propose Dual data Mapping sys DDMS;It beat gpt4 in certain entity matching tasks+automates AAS instance creation | T28: genai enable seamless integr of heterogeneous mfg data;improve semantic consistency,+supports scalable dt generation for enhanced interoperability | U28: the deployment of genai enabled by domianspecific fine tunning of llms;structured vocabularies like ECLASS,+modular standardized information modles SMTs within AAS fw | V28: a major challenge semantic ambiguity in manufacturer data+lack of existing automated methods for intelligent | W28: Align – GenAI links legacy system data with standard models like AAS by semantically matching and integrating heterogeneous data sources. | X28: fine tunw Llama2 llm for entity matching tasks | Y28: DT, Uses a fine-tuned LLM to match proprietary manufacturing data to Asset Administration Shells | Z28: 4 | AA28: 4 | AB28: Lab validation | AC28: Integration component testing | AD28: Assistive GenAI | AE28: Y | AG28: Implements a fine-tuned open-source LLM within a dual data mapping system connected to Asset Administration Shell servers and concept catalogs, validated via injection-molding case studies but not deployed in continuous plant operations. | AH28: LLM suggests and ranks mappings between heterogeneous attribute schemas for engineers, semi-automating interoperability modelling, yet humans still supervise, approve or correct mappings before use in downstream engineering tools. | AK28: {=_xlfn.IFS(AC28="Principles observation",1, AC28="Concept formulation",2, AC28="Proof-of-concept simulation", 3, AC28="Core function validation", 4, AC28="Integration component testing", 5, AC28="Component validation in relevant environment", 6, AC28="Subsystem demonstration in relevant environment", 7, AC28="System demonstration in operational environment", 8, AC28="Production qualification", 9, AC28="Mission-proven operations", 10)} -> 5 | AL28: {=_xlfn.IFS(AD28="Assistive GenAI", 1, AD28="GenAI-led with human oversight", 2, AD28="Autonomous process learning", 3)} -> 1
A29: 30 | B29: FCLLM-DT: Enpowering Federated Continual Learning With Large Language Models for Digital-Twin-Based Industrial IoT | C29: Xia Y.; Chen Y.; Zhao Y.; Kuang L.; Liu X.; Hu J.; Liu Z. | D29: 2025 | E29: IEEE Internet of Things Journal | F29: 4 | G29: =IFERROR(LEFT(C29, FIND(";", C29) - 1), C29) -> Xia Y. | H29: Micro-Electronics Research Institute, Hangzhou Dianzi University, Hangzhou, 310005, China | I29: Digital twins (DTs); federated continual learning (FCL); large language model (LLM); machinery fault diagnosis; retrieval-augmented generation (RAG) | J29: =IF(OR( E29="International Journal of Production Research", E29="Journal of Manufacturing Technology Management", E29="International Journal of Production Economics", E29="Journal of Industrial Information Integration", E29="Transportation Research Part E: Logistics and Transportation Review", E29="Journal of Cleaner Production", E29="MM 2024 - Proceedings of the 32nd ACM International Conference on Multimedia", E29="Oeconomia Copernicana", E29="Technology in Society" ), "MGT", "ENG") -> ENG | K29: empirical | L29: Design science research | M29: Techniques; Applications | N29: Manufacturing | O29: fault diagnosis | P29: Machinery | R29: LLM chatbot | S29: the proposed FCllmdt scheme;combining digitaltwinbased anomaly repair;retrievalaugmented llm data generation,+federated continual learning;improve bearingfault diag acc+sensordata qual | T29: rag llm supplies highfidelity virtual sensor streams+augments scarce or faulty data;boosting diagnostic acc+enabling privacysafe collabration across distributed plants | U29: rag knowlege bases of historical data | W29: Augment – LLM generates synthetic bearing signals to replace missing or corrupted sensor data, enriching training sets. | X29: ragchatgpt produces timeseries data | Y29: synthetic bearing signals | Z29: 4 | AA29: 3 | AB29: Lab validation | AC29: Core function validation | AD29: Assistive GenAI | AE29: Y | AG29: Integrates DT, RAG-assisted LLM, and federated continual learning for bearing fault diagnosis, validated on CWRU and MFPT datasets in a controlled compute environment; no real-time deployment, plant integration, or operational IIoT rollout is shown. | AH29: The LLM is used in a RAG loop to generate virtual time-series data and support anomaly repair for training diagnostic models; it never directly controls equipment or executes maintenance, acting purely as a data/learning assistant. | AK29: {=_xlfn.IFS(AC29="Principles observation",1, AC29="Concept formulation",2, AC29="Proof-of-concept simulation", 3, AC29="Core function validation", 4, AC29="Integration component testing", 5, AC29="Component validation in relevant environment", 6, AC29="Subsystem demonstration in relevant environment", 7, AC29="System demonstration in operational environment", 8, AC29="Production qualification", 9, AC29="Mission-proven operations", 10)} -> 4 | AL29: {=_xlfn.IFS(AD29="Assistive GenAI", 1, AD29="GenAI-led with human oversight", 2, AD29="Autonomous process learning", 3)} -> 1
A30: 31 | B30: Large language model assisted fine-grained knowledge graph construction for robotic fault diagnosis | C30: Liao X.; Chen C.; Wang Z.; Liu Y.; Wang T.; Cheng L. | D30: 2025 | E30: Advanced Engineering Informatics | F30: 4 | G30: =IFERROR(LEFT(C30, FIND(";", C30) - 1), C30) -> Liao X. | H30: Guangdong Provincial Key Laboratory of Cyber-Physical System, Guangdong University of Technology, Guangzhou, China | I30: Fault Diagnosis; Industrial Robots; Knowledge Graph; Large Language Model | J30: =IF(OR( E30="International Journal of Production Research", E30="Journal of Manufacturing Technology Management", E30="International Journal of Production Economics", E30="Journal of Industrial Information Integration", E30="Transportation Research Part E: Logistics and Transportation Review", E30="Journal of Cleaner Production", E30="MM 2024 - Proceedings of the 32nd ACM International Conference on Multimedia", E30="Oeconomia Copernicana", E30="Technology in Society" ), "MGT", "ENG") -> ENG | K30: empirical | L30: Design science research | M30: Techniques | N30: Manufacturing | O30: fault diagnosis | P30: Machinery | R30: data augmentation | S30: the llmassisted pipeline assInNNER+ANLM+CFM lifts nestedNER F1 by up to 8.25 % | T30: genai augments scarce maint texts+refines ontology;producing more accurate;actionable kg | V30: firms reluctance to share proprietary fault logs | W30: Augment – LLMs generate and label synthetic robotic-fault text, enriching sparse maintenance datasets for model training. | X30: anlm w/industrial template;confidence filter;lorafine tunw bert backbone | Y30: genAI for fault text data augmentation | Z30: 4 | AA30: 3 | AB30: Lab validation | AC30: Core function validation | AD30: Assistive GenAI | AE30: Y | AG30: Proposes an LLM-assisted pipeline for fine-grained KG construction in robotic fault diagnosis; evaluates nested NER and data augmentation on industrial text corpora, but remains an offline algorithmic study without integration into maintenance workflows or systems. | AH30: The LLM extracts entities and relations to build a richer fault knowledge graph that can support engineers, but it neither recommends concrete actions nor interfaces with robots; humans retain full diagnostic and operational control. | AK30: {=_xlfn.IFS(AC30="Principles observation",1, AC30="Concept formulation",2, AC30="Proof-of-concept simulation", 3, AC30="Core function validation", 4, AC30="Integration component testing", 5, AC30="Component validation in relevant environment", 6, AC30="Subsystem demonstration in relevant environment", 7, AC30="System demonstration in operational environment", 8, AC30="Production qualification", 9, AC30="Mission-proven operations", 10)} -> 4 | AL30: {=_xlfn.IFS(AD30="Assistive GenAI", 1, AD30="GenAI-led with human oversight", 2, AD30="Autonomous process learning", 3)} -> 1
A31: 32 | B31: ChatCNC: Conversational machine monitoring via large language model and real-time data retrieval augmented generation | C31: Jeon J.; Sim Y.; Lee H.; Han C.; Yun D.; Kim E.; Nagendra S.L.; Jun M.B.G.; Kim Y.; Lee S.W.; Lee J. | D31: 2025 | E31: Journal of Manufacturing Systems | F31: 3 | G31: =IFERROR(LEFT(C31, FIND(";", C31) - 1), C31) -> Jeon J. | H31: School of Mechanical Engineering, Pusan National University, Busan, 46241, South Korea | I31: Conversational machine monitoring; Human-Centric Smart Manufacturing (HCSM); Human-data interaction; Large-Language Model (LLM); Real-time Retrieval Augmented Generation (RAG) | J31: =IF(OR( E31="International Journal of Production Research", E31="Journal of Manufacturing Technology Management", E31="International Journal of Production Economics", E31="Journal of Industrial Information Integration", E31="Transportation Research Part E: Logistics and Transportation Review", E31="Journal of Cleaner Production", E31="MM 2024 - Proceedings of the 32nd ACM International Conference on Multimedia", E31="Oeconomia Copernicana", E31="Technology in Society" ), "MGT", "ENG") -> ENG | K31: empirical | L31: Design science research | M31: Techniques | N31: Manufacturing | O31: process monitoring | P31: Machinery | R31: LLM agents | S31: chatCNC translates NL queries into SQL;retrieves live IIoT data,+answers w/93.3 % acc;contextual+exemplar prompting markedly reduce hallucinations+retrieval failures | T31: llm helps op access realtime machine info w/o data engineers;improving humancentric smart mfg+decision speed | V31: op low digital literacy;llm hallucination;privacy limits on data sharing | W31: Align – LLM maps operator language to CNC database queries, composes context-aware answers, linking speech to shop-floor knowledge | X31: agents gen SQL;rag w/JSON;MTConnect stream;loragpt4 prompts | Y31: LLM agents | Z31: 4 | AA31: 3 | AB31: Field pilots | AC31: Component validation in relevant environment | AD31: Assistive GenAI | AE31: Y | AG31: Implements a multi-agent LLM framework connected via MTConnect/MySQL to a real CNC on a shop floor, answering live monitoring queries; validated with accuracy metrics and usability study but not yet deployed plant-wide. | AH31: ChatCNC retrieves and summarizes machine data, explaining conditions and trends, but leaves interpretation and any parameter changes to human operators; it augments situational awareness without initiating or executing control actions. | AK31: {=_xlfn.IFS(AC31="Principles observation",1, AC31="Concept formulation",2, AC31="Proof-of-concept simulation", 3, AC31="Core function validation", 4, AC31="Integration component testing", 5, AC31="Component validation in relevant environment", 6, AC31="Subsystem demonstration in relevant environment", 7, AC31="System demonstration in operational environment", 8, AC31="Production qualification", 9, AC31="Mission-proven operations", 10)} -> 6 | AL31: {=_xlfn.IFS(AD31="Assistive GenAI", 1, AD31="GenAI-led with human oversight", 2, AD31="Autonomous process learning", 3)} -> 1
A32: 33 | B32: Leveraging large language models for Human-Machine collaborative troubleshooting of complex industrial equipment faults | C32: Wen S.; Li F.; Zhuang W.; Pan X.; Yu W.; Bao J.; Li X. | D32: 2025 | E32: Advanced Engineering Informatics | F32: 3 | G32: =IFERROR(LEFT(C32, FIND(";", C32) - 1), C32) -> Wen S. | H32: College of Mechanical Engineering, Donghua University, Shanghai, 201620, China | I32: Fault Troubleshooting; Human-Machine Collaboration; Industrial Knowledge Graph; Knowledge Extraction and Reasoning; Large Language Models | J32: =IF(OR( E32="International Journal of Production Research", E32="Journal of Manufacturing Technology Management", E32="International Journal of Production Economics", E32="Journal of Industrial Information Integration", E32="Transportation Research Part E: Logistics and Transportation Review", E32="Journal of Cleaner Production", E32="MM 2024 - Proceedings of the 32nd ACM International Conference on Multimedia", E32="Oeconomia Copernicana", E32="Technology in Society" ), "MGT", "ENG") -> ENG | K32: empirical | L32: Design science research | M32: Techniques | N32: Manufacturing | O32: fault diagnosis | P32: Machinery | Q32: 5-Why root-cause analysis; human–machine collaboration | R32: LLM chatbot | S32: gpt4 semantically extracting fault entities;relations+5Why chains from manuals+471 fault tickets;resulting in Enhanced casual Fault kg ECFkg w/95.7 % triple acc;combined w/llm agent for interactive diagnostic troubleshooting | T32: gpt4 helps building kg by semantically extracting fault entities;relations+5Why chains;llm agent building on rag+kg for interactive diagnostic troubleshooting> cuts troubleshooting time | U32: semantically lossless prompt templates for extraction;humaninloop dialogue loop | V32: scarce/lossy fault data;limitd sensors in corrosive environments,+semantic ambiguity in op tickets | W32: Align & Reason – GPT-4 aligns text to knowledge graph and reasons interactively with technicians to pinpoint equipment faults. | X32: gpt4 for knowlege semantic parsing+extraction | Y32: LLM-enabled knowledge semantic parsing and extraction for building a KG | Z32: 4 | AA32: 3 | AB32: Lab validation | AC32: Core function validation | AD32: Assistive GenAI | AE32: Y | AG32: Develops an enhanced causal fault knowledge graph and interactive troubleshooting method for bridge cranes; constructs graphs from manuals and fault tickets, tunes embedding models, and compares diagnosis performance, but only on historical cases and simulations. | AH32: The LLM-KG system suggests likely fault chains and troubleshooting steps given symptoms, while technicians iteratively confirm causes and perform checks; it guides reasoning but does not operate or reconfigure equipment autonomously. | AK32: {=_xlfn.IFS(AC32="Principles observation",1, AC32="Concept formulation",2, AC32="Proof-of-concept simulation", 3, AC32="Core function validation", 4, AC32="Integration component testing", 5, AC32="Component validation in relevant environment", 6, AC32="Subsystem demonstration in relevant environment", 7, AC32="System demonstration in operational environment", 8, AC32="Production qualification", 9, AC32="Mission-proven operations", 10)} -> 4 | AL32: {=_xlfn.IFS(AD32="Assistive GenAI", 1, AD32="GenAI-led with human oversight", 2, AD32="Autonomous process learning", 3)} -> 1
A33: 34 | B33: A blockchain-based LLM-driven energy-efficient scheduling system towards distributed multi-agent manufacturing scenario of new energy vehicles within the circular economy | C33: Liu C.; Nie Q. | D33: 2025 | E33: Computers and Industrial Engineering | F33: 2 | G33: =IFERROR(LEFT(C33, FIND(";", C33) - 1), C33) -> Liu C. | H33: College of Mechanical and Electrical Engineering, Nanjing University of Aeronautics and Astronautics, Nanjing, 210016, China | I33: Blockchain; Circular economy; Distributed manufacturing; Energy-efficient scheduling; Large language model; Multi-agent | J33: =IF(OR( E33="International Journal of Production Research", E33="Journal of Manufacturing Technology Management", E33="International Journal of Production Economics", E33="Journal of Industrial Information Integration", E33="Transportation Research Part E: Logistics and Transportation Review", E33="Journal of Cleaner Production", E33="MM 2024 - Proceedings of the 32nd ACM International Conference on Multimedia", E33="Oeconomia Copernicana", E33="Technology in Society" ), "MGT", "ENG") -> ENG | K33: empirical | L33: Design science research | M33: Techniques | N33: Manufacturing | O33: process planning | P33: automotive | Q33: Circular-economy principles | R33: LLM agents | S33: gpt4 agent receives realtime task;machine+energy data from blockchainverified factories;interprets constaints;reasons through learned scheduling patterns,+outputs energyoptimal sequencing commands to multiagent shopfloors for distributed mfg | T33: enable adaptive;lowenergy distributed prod;boosting eff+circulareconomy perf in EV mfg | U33: trustworthy data access w/credit evaluationbased consensus mechanism | V33: untrusted factory data can mislead llm;largescale consensus may add latency | W33: Reason – LLM reasons over live agent data to generate energy-optimal, delay-aware production schedules | X33: promptdriven gpt4 | Y33: too complicated | Z33: 4 | AA33: 3 | AB33: Lab validation | AC33: Integration component testing | AD33: Autonomous process learning | AE33: Y | AG33: Implements a full prototype combining LLM scheduler, multi-agent control, and blockchain consensus on cloud servers, validated via case study and throughput tests using realistic new-energy-vehicle data, but not yet integrated into live factories. | AH33: LLM-based decision agent autonomously generates multi-objective energy-efficient schedules and selects agents via bids; machine agents then execute plans, while humans define objectives, prompts, and constraints rather than approving each dispatch manually. | AK33: {=_xlfn.IFS(AC33="Principles observation",1, AC33="Concept formulation",2, AC33="Proof-of-concept simulation", 3, AC33="Core function validation", 4, AC33="Integration component testing", 5, AC33="Component validation in relevant environment", 6, AC33="Subsystem demonstration in relevant environment", 7, AC33="System demonstration in operational environment", 8, AC33="Production qualification", 9, AC33="Mission-proven operations", 10)} -> 5 | AL33: {=_xlfn.IFS(AD33="Assistive GenAI", 1, AD33="GenAI-led with human oversight", 2, AD33="Autonomous process learning", 3)} -> 3
A34: 35 | B34: An intelligent energy management method for the manufacturing systems using the knowledge graph and large language model | C34: Wu P.; Tu H.; Mou X.; Gong L. | D34: 2025 | E34: Journal of Intelligent Manufacturing | F34: 2 | G34: =IFERROR(LEFT(C34, FIND(";", C34) - 1), C34) -> Wu P. | H34: College of Artificial Intelligence, Southwest University, Chongqing, 400715, China | I34: Energy knowledge graph; Energy management; Inference ability; Large Language Models; Manufacturing systems | J34: =IF(OR( E34="International Journal of Production Research", E34="Journal of Manufacturing Technology Management", E34="International Journal of Production Economics", E34="Journal of Industrial Information Integration", E34="Transportation Research Part E: Logistics and Transportation Review", E34="Journal of Cleaner Production", E34="MM 2024 - Proceedings of the 32nd ACM International Conference on Multimedia", E34="Oeconomia Copernicana", E34="Technology in Society" ), "MGT", "ENG") -> ENG | K34: empirical | L34: Design science research | M34: Techniques | N34: Manufacturing | O34: process monitoring | P34: Machinery | R34: KG‑augmented LLM | S34: use genaibased bertTransformerCRF modle to extract energy knowlege+build kg;then use kg to finetune llm;then answer energyrelated questions kgbased rag | T34: kgaugmented llm provides highly accurate;lowhallucination energymanagement advice;helping shops cut power costs+meet sustainability pressures | U34: edgecloud architecture;realtime powermeter integr | V34: noisy shopfloor data;limitd labelled energy knowlege;hardware latency at factory edge | W34: Align & Reason – LLM extracts and structures energy facts into a KG (Align), then reasons via KG-RAG to deliver optimisation answers | X34: bitic BERTITCRF for KF construction;gptbased llm+prefixtuning;BiLSTMCRF subgraphs | Y34: LLM to extract and build KG; embed KG into LLM | Z34: 4 | AA34: 3 | AB34: Lab validation | AC34: Core function validation | AD34: Assistive GenAI | AE34: Y | AG34: Constructs an energy knowledge graph and EKG-embedded LLM using two-years of milling center data; answers energy management questions evaluated by experts, but runs as an offline advisory model without integration into plant control loops. | AH34: The model recommends monitoring setups, parameter choices, and reduction strategies for machine energy use, yet humans decide implementation and adjust equipment; GenAI never directly executes control or optimization actions. | AK34: {=_xlfn.IFS(AC34="Principles observation",1, AC34="Concept formulation",2, AC34="Proof-of-concept simulation", 3, AC34="Core function validation", 4, AC34="Integration component testing", 5, AC34="Component validation in relevant environment", 6, AC34="Subsystem demonstration in relevant environment", 7, AC34="System demonstration in operational environment", 8, AC34="Production qualification", 9, AC34="Mission-proven operations", 10)} -> 4 | AL34: {=_xlfn.IFS(AD34="Assistive GenAI", 1, AD34="GenAI-led with human oversight", 2, AD34="Autonomous process learning", 3)} -> 1
A35: 36 | B35: LLM-MANUF: An integrated framework of Fine-Tuning large language models for intelligent Decision-Making in manufacturing | C35: Du K.; Yang B.; Xie K.; Dong N.; Zhang Z.; Wang S.; Mo F. | D35: 2025 | E35: Advanced Engineering Informatics | F35: 2 | G35: =IFERROR(LEFT(C35, FIND(";", C35) - 1), C35) -> Du K. | H35: State Key Laboratory of Mechanical Transmission for Advanced Equipment, Chongqing University, Chongqing, 400044, China | I35: Fine-Tuning; Integrated Framework; Intelligent Decision-Making; Large Language Model; Manufacturing | J35: =IF(OR( E35="International Journal of Production Research", E35="Journal of Manufacturing Technology Management", E35="International Journal of Production Economics", E35="Journal of Industrial Information Integration", E35="Transportation Research Part E: Logistics and Transportation Review", E35="Journal of Cleaner Production", E35="MM 2024 - Proceedings of the 32nd ACM International Conference on Multimedia", E35="Oeconomia Copernicana", E35="Technology in Society" ), "MGT", "ENG") -> ENG | K35: empirical | L35: Design science research | M35: Techniques | N35: Operations | O35: fault diagnosis; maintenance | P35: automotive | R35: LLM chatbot | S35: the llmMANUF fw consisting of multiple loratuned llms+DWMOE ranking+adaptive fusion;beat any single fine tunw modle in intelligent decisionmaking in mfg | T35: improve acc+reliabilty of O&M decision plans;reduce decision bias,+achieves nearstateofart perf w/lower compute+faster responce than very large | U35: domianspecific fine tunning corpus built from 23k semistructured O&M records;parallel fine tunw llms | V35: semistructured data requiring preprocessing;compute/time tradeoffs | W35: Align & Reason — Fine-tuned LLM aligns operator language to Operaitona&Maintenance knowledge, then reasons, parsing fault descriptions and synthesizing maintenance decision plans to support human decision making | X35: multiple loratuned llms+DWMOE ranking+adaptive fusion | Y35: LLM for fault diagnosis for decision-making: a framework with fine-tuning LLM ensemble + rank + fusion | Z35: 4 | AA35: 4 | AB35: Lab validation | AC35: Core function validation | AD35: Assistive GenAI | AE35: Y | AG35: Implements and evaluates a fine-tuned LLM integration framework on an offline O&M text dataset from one automotive enterprise; no live connections to enterprise systems or operational deployment. | AH35: Framework outputs ranked decision plans as text for engineers; it does not trigger or execute control actions, so humans remain sole decision makers and implementers in manufacturing processes. | AK35: {=_xlfn.IFS(AC35="Principles observation",1, AC35="Concept formulation",2, AC35="Proof-of-concept simulation", 3, AC35="Core function validation", 4, AC35="Integration component testing", 5, AC35="Component validation in relevant environment", 6, AC35="Subsystem demonstration in relevant environment", 7, AC35="System demonstration in operational environment", 8, AC35="Production qualification", 9, AC35="Mission-proven operations", 10)} -> 4 | AL35: {=_xlfn.IFS(AD35="Assistive GenAI", 1, AD35="GenAI-led with human oversight", 2, AD35="Autonomous process learning", 3)} -> 1
A36: 37 | B36: Empowering LLMs by hybrid retrieval-augmented generation for domain-centric Q&A in smart manufacturing | C36: Wan Y.; Chen Z.; Liu Y.; Chen C.; Packianather M. | D36: 2025 | E36: Advanced Engineering Informatics | F36: 2 | G36: =IFERROR(LEFT(C36, FIND(";", C36) - 1), C36) -> Wan Y. | H36: Department of Mechanical Engineering, School of Engineering, Cardiff University, Cardiff, CF24 3AA, United Kingdom | I36: Additive manufacturing; Design for additive manufacturing; Knowledge graph; Large language model; Q&A; Retrieval-augmented generation; Smart manufacturing | J36: =IF(OR( E36="International Journal of Production Research", E36="Journal of Manufacturing Technology Management", E36="International Journal of Production Economics", E36="Journal of Industrial Information Integration", E36="Transportation Research Part E: Logistics and Transportation Review", E36="Journal of Cleaner Production", E36="MM 2024 - Proceedings of the 32nd ACM International Conference on Multimedia", E36="Oeconomia Copernicana", E36="Technology in Society" ), "MGT", "ENG") -> ENG | K36: empirical | L36: Design science research | M36: Techniques | N36: Design | O36: additive manufacturing | R36: LLM chatbot | S36: a hybrid kgVector rag w/semantic alignment+prompt engineering outperformed vectoronly+kgonly baselines on;addressing precisionscalability tradeoffs | T36: the approach improve answer acc+contextual relevance for domiancentric mfg Q&A+lowers barrier to | U36: kg from domian corpora;prompt enhancement w/humaninloop vaild | V36: general llms suffer domian gaps;outdated knowlege,+hallucinations | W36: Align & Reason — Align: RAG links queries to domain KG and vetted corpora via constraints and prompts. Reason: LLM synthesizes KG relations and retrieved texts into coherent, context-aware answers | X36: hybrid kgrag for Design for additive mfg DfAM decision suport/domian Q&A | Y36: Hybrid KG-RAG | Z36: 4 | AA36: 3 | AB36: Lab validation | AC36: Core function validation | AD36: Assistive GenAI | AE36: Y | AG36: Proposes a hybrid KG-vector RAG architecture and evaluates Q&A accuracy on curated DfAM corpora; system remains an experimental Q&A prototype without integration to plant IT/OT infrastructure. | AH36: LLM answers engineering design and manufacturing questions but only supplies information and recommendations; humans still interpret responses and decide any downstream design or process changes. | AK36: {=_xlfn.IFS(AC36="Principles observation",1, AC36="Concept formulation",2, AC36="Proof-of-concept simulation", 3, AC36="Core function validation", 4, AC36="Integration component testing", 5, AC36="Component validation in relevant environment", 6, AC36="Subsystem demonstration in relevant environment", 7, AC36="System demonstration in operational environment", 8, AC36="Production qualification", 9, AC36="Mission-proven operations", 10)} -> 4 | AL36: {=_xlfn.IFS(AD36="Assistive GenAI", 1, AD36="GenAI-led with human oversight", 2, AD36="Autonomous process learning", 3)} -> 1
A37: 38 | B37: A generative pre-trained transformer industrial bot to improve operators’ working experience in a small Industry 5.0 factory | C37: Kiangala K.S.; Wang Z. | D37: 2025 | E37: International Journal of Advanced Manufacturing Technology | F37: 2 | G37: =IFERROR(LEFT(C37, FIND(";", C37) - 1), C37) -> Kiangala K.S. | H37: Department of Electrical and Smart Systems Engineering, University of South Africa (UNISA), Florida, Gauteng, Johannesburg, 1709, South Africa | I37: Artificial intelligence (AI); Generative pre-trained transformer (GPT); Industrial chatbot; Industry 4.0; Industry 5.0 | J37: =IF(OR( E37="International Journal of Production Research", E37="Journal of Manufacturing Technology Management", E37="International Journal of Production Economics", E37="Journal of Industrial Information Integration", E37="Transportation Research Part E: Logistics and Transportation Review", E37="Journal of Cleaner Production", E37="MM 2024 - Proceedings of the 32nd ACM International Conference on Multimedia", E37="Oeconomia Copernicana", E37="Technology in Society" ), "MGT", "ENG") -> ENG | K37: empirical | L37: Case study | M37: Applications | N37: Manufacturing | O37: process monitoring; fault diagnosis; maintenance; Work instructions for operators (task Q&A) | Q37: Industry 5.0 human-centric & sustainability paradigm | R37: LLM chatbot | S37: a gpt4 industrial bot online/offline helps op monitor prod;check overtime/pollution safe;discover faults;perform rootcause analysis,+gen synthetic data | T37: chatbot improve productivity;shortens downtime;enhance decision suport+training,+supports safer;humancentric ops by considering overtime limits+pollution thresholds | U37: customizing gpt4 w/factory CSV data w/LangChain;simple NL interface;clear I5.0 safe parameters overtime/pollution | V37: security tradeoff of online data exposure;offline versions limitd computation/context;SMEs lack practical prototypes+resorces | W37: Enhance — Connects CSV data to GPT-4 and generates synthetic data for modelling. Decide — Analyzes KPIs, faults, overtime and pollution to recommend safe actions. | X37: upload CSV to chatgpt for factory troubleshootong;op well,+data augmentation Two industrial bot versions;The first offline version;created using Langchain agent connected to gpt4 LM through openai APIs+visualized w/Streamlit | Z37: 5 | AA37: 3 | AB37: Field pilots | AC37: Component validation in relevant environment | AD37: Assistive GenAI | AE37: N | AF37: Lab validation – Core function validation | AG37: Develops online and offline GPT-based chatbots trained on CSV data from an experimental bottling plant; demonstrates use cases via prompts, but PLC/SCADA integration and automatic execution remain assumed, not implemented. | AH37: Industrial bot monitors production, diagnoses faults, and suggests overtime or parameter adjustments through natural-language dialogue; operators ultimately decide actions and implement any changes on shop-floor systems. | AK37: {=_xlfn.IFS(AC37="Principles observation",1, AC37="Concept formulation",2, AC37="Proof-of-concept simulation", 3, AC37="Core function validation", 4, AC37="Integration component testing", 5, AC37="Component validation in relevant environment", 6, AC37="Subsystem demonstration in relevant environment", 7, AC37="System demonstration in operational environment", 8, AC37="Production qualification", 9, AC37="Mission-proven operations", 10)} -> 6 | AL37: {=_xlfn.IFS(AD37="Assistive GenAI", 1, AD37="GenAI-led with human oversight", 2, AD37="Autonomous process learning", 3)} -> 1
A38: 39 | B38: A large language model-enabled machining process knowledge graph construction method for intelligent process planning | C38: Xu Q.; Qiu F.; Zhou G.; Zhang C.; Ding K.; Chang F.; Lu F.; Yu Y.; Ma D.; Liu J. | D38: 2025 | E38: Advanced Engineering Informatics | F38: 1 | G38: =IFERROR(LEFT(C38, FIND(";", C38) - 1), C38) -> Xu Q. | H38: School of Mechanical Engineering, Xi'an Jiaotong University, Xi'an, 710049, China | I38: Intelligent process planning; Knowledge graphs; Large language models; Machining process | J38: =IF(OR( E38="International Journal of Production Research", E38="Journal of Manufacturing Technology Management", E38="International Journal of Production Economics", E38="Journal of Industrial Information Integration", E38="Transportation Research Part E: Logistics and Transportation Review", E38="Journal of Cleaner Production", E38="MM 2024 - Proceedings of the 32nd ACM International Conference on Multimedia", E38="Oeconomia Copernicana", E38="Technology in Society" ), "MGT", "ENG") -> ENG | K38: empirical | L38: Design science research | M38: Techniques | N38: Manufacturing | O38: Process planning | P38: Machinery | R38: LLM enabled KG | S38: an llmenabled pipeline gpt4 preannotation → LERTCRF verifier → lorafine tunw MPKEgpt builds machining proc kg;cutting construction time 48.58%;cost 46.44%,+improving F1 by 1.96% versus deeplearning baselines | T38: faster;cheaper,+more accurate proc knowlege capture;resulting MPkg supports intelligent proc planing+kgbased Q&A | U38: expert reannotation;curated datasets | V38: llm hallucination+limitd domian generalization;reliance on domian experts;token/annotation costs;need for highqual labeled corpora | W38: Enhance — Annotates extracts and structures machining knowledge into a KG to strengthen planning and decision support. | X38: gpt4 preannotation;LERTCRF verifier;lora fine tunw MPKEgpt;SWRL fusion | Y38: using LLM to construct a KG (NER) | Z38: 5 | AA38: 4 | AB38: Lab validation | AC38: Core function validation | AD38: Assistive GenAI | AE38: Y | AG38: Uses LLMs to pre-annotate machining texts, builds a verifier and MPKE-GPT, and constructs MPKG plus prototype system from 50 enterprise parts; evaluation relies on offline datasets and metrics. | AH38: System extracts and structures process knowledge to support planners; it generates or exposes information but does not autonomously issue CNC instructions or modify process parameters. | AK38: {=_xlfn.IFS(AC38="Principles observation",1, AC38="Concept formulation",2, AC38="Proof-of-concept simulation", 3, AC38="Core function validation", 4, AC38="Integration component testing", 5, AC38="Component validation in relevant environment", 6, AC38="Subsystem demonstration in relevant environment", 7, AC38="System demonstration in operational environment", 8, AC38="Production qualification", 9, AC38="Mission-proven operations", 10)} -> 4 | AL38: {=_xlfn.IFS(AD38="Assistive GenAI", 1, AD38="GenAI-led with human oversight", 2, AD38="Autonomous process learning", 3)} -> 1
A39: 40 | B39: An LLM-enabled human demonstration-assisted hybrid robot skill synthesis approach for human-robot collaborative assembly | C39: Yin Y.; Wan K.; Li C.; Zheng P., (2) | D39: 2025 | E39: CIRP Annals | F39: 1 | G39: =IFERROR(LEFT(C39, FIND(";", C39) - 1), C39) -> Yin Y. | H39: Department of Industrial and Systems Engineering, The Hong Kong Polytechnic University, Hong Kong Special Administrative Region, China | I39: Human robot collaboration; human-guided robot learning; manufacturing system | J39: =IF(OR( E39="International Journal of Production Research", E39="Journal of Manufacturing Technology Management", E39="International Journal of Production Economics", E39="Journal of Industrial Information Integration", E39="Transportation Research Part E: Logistics and Transportation Review", E39="Journal of Cleaner Production", E39="MM 2024 - Proceedings of the 32nd ACM International Conference on Multimedia", E39="Oeconomia Copernicana", E39="Technology in Society" ), "MGT", "ENG") -> ENG | K39: empirical | L39: Design science research | M39: Techniques | N39: Manufacturing | O39: human–robot collaboration; assembly | P39: Machinery | R39: LLM agents | S39: the threelayer multimodal llm agent for languagetoreward translation achieved 100% rewardcode success 20/20,+memoryenhanced hybrid;outperforming BC+PPO alone on HRCA tasks | T39: removes expertdependent reward engineering;accelerates robot skill learning from NL,+improve collaborativeassembly task success+policy convergence | U39: structured;example+rulerich prompts | V39: safe constaints must respected | W39: Enhance — Translates natural-language instructions into structured reward components and motion descriptors for learning. Decide — Decomposes tasks and parameterises rewards, guiding DRL policy search toward feasible assembly behaviours. | Y39: Multimodal LLM agent for language-to-reward translation; LLM-guided task decomposition & motion description | Z39: 4 | AA39: 3 | AB39: Lab validation | AC39: Integration component testing | AD39: GenAI-led with human oversight | AE39: Y | AG39: Combines LLM-based reward design, LfD, DRL, MR-HMD, and a UR5 cobot; validated on multiple collaborative assembly tasks in a controlled lab cell, not on production lines. | AH39: LLM designs rewards and orchestrates skill composition while DRL policies autonomously generate robot actions; humans provide demonstrations, task goals, and corrections, supervising performance and safety during collaborative assembly. | AK39: {=_xlfn.IFS(AC39="Principles observation",1, AC39="Concept formulation",2, AC39="Proof-of-concept simulation", 3, AC39="Core function validation", 4, AC39="Integration component testing", 5, AC39="Component validation in relevant environment", 6, AC39="Subsystem demonstration in relevant environment", 7, AC39="System demonstration in operational environment", 8, AC39="Production qualification", 9, AC39="Mission-proven operations", 10)} -> 5 | AL39: {=_xlfn.IFS(AD39="Assistive GenAI", 1, AD39="GenAI-led with human oversight", 2, AD39="Autonomous process learning", 3)} -> 2
A40: 42 | B40: An automatic machine fault identification method using the knowledge graph–embedded large language model | C40: Wu P.; Mou X.; Gong L.; Tu H.; Qiu L.; Yang B. | D40: 2025 | E40: International Journal of Advanced Manufacturing Technology | F40: 1 | G40: =IFERROR(LEFT(C40, FIND(";", C40) - 1), C40) -> Wu P. | H40: College of Artificial Intelligence, Southwest University, Chongqing, 400715, China | I40: Fault localization; Knowledge graph; Knowledge inference; Large language model; Machining process | J40: =IF(OR( E40="International Journal of Production Research", E40="Journal of Manufacturing Technology Management", E40="International Journal of Production Economics", E40="Journal of Industrial Information Integration", E40="Transportation Research Part E: Logistics and Transportation Review", E40="Journal of Cleaner Production", E40="MM 2024 - Proceedings of the 32nd ACM International Conference on Multimedia", E40="Oeconomia Copernicana", E40="Technology in Society" ), "MGT", "ENG") -> ENG | K40: empirical | L40: Design science research | M40: Techniques | N40: Manufacturing | O40: fault diagnosis; maintenance | P40: Machinery | R40: KG‑augmented LLM | S40: the MPkgembedded llm achieves 97.50% acc Pr 96.67%;Re 98.30%+higher inference/usability scores 9.1/9.4 than kg;llm,+kgllm baselines;kg guidance reduce hallucinations in machining fault diag | T40: integrating kg+llm improve fault localization;speeds troubleshooting,+provides usable advice for industrial machining scenarios versus conventional expert sys | U40: domian ontology+BTC NER to build MPkg;edgecloud data pipeline OPC UA;sensors;ERP/MES enabling real deployments | V40: residual knowlege boundary on unseen conditions;heavy preprocessing/feature reorganization needs;total processing latency data transfer noted;suggesting improved IoT architecture | W40: Enhance — Embeds KG structure into the LLM to enrich knowledge and curb hallucinations. Decide — Infers root causes and proposes troubleshooting actions from symptoms in machining scenarios | X40: kg structure encoded into embeddings structural embeddings;entity/relation embeddings+fused into llms representation space during lora fine tunning | Y40: KG‑augmented LLM: fine-tune LLM using KG embeddings | Z40: 4 | AA40: 3 | AB40: Lab validation | AC40: Core function validation | AD40: Assistive GenAI | AE40: Y | AG40: The KG+LLM expert system is evaluated on industrial CNC fault cases and user studies, but only via functional tests and deployment diagrams. No evidence of live connection to shop-floor assets or real-time plant deployment. | AH40: The system analyzes fault descriptions, reasons over the KG, and proposes root causes and maintenance advice. It does not execute actions on machines; human maintainers still decide and implement troubleshooting steps. | AK40: {=_xlfn.IFS(AC40="Principles observation",1, AC40="Concept formulation",2, AC40="Proof-of-concept simulation", 3, AC40="Core function validation", 4, AC40="Integration component testing", 5, AC40="Component validation in relevant environment", 6, AC40="Subsystem demonstration in relevant environment", 7, AC40="System demonstration in operational environment", 8, AC40="Production qualification", 9, AC40="Mission-proven operations", 10)} -> 4 | AL40: {=_xlfn.IFS(AD40="Assistive GenAI", 1, AD40="GenAI-led with human oversight", 2, AD40="Autonomous process learning", 3)} -> 1
A41: 43 | B41: IIoT-enabled digital twin for legacy and smart factory machines with LLM integration | C41: Gautam A.; Aryal M.R.; Deshpande S.; Padalkar S.; Nikolaenko M.; Tang M.; Anand S. | D41: 2025 | E41: Journal of Manufacturing Systems | F41: 1 | G41: =IFERROR(LEFT(C41, FIND(";", C41) - 1), C41) -> Gautam A. | H41: Center for Global Design and Manufacturing, Siemens Simulation Technology Center, Department of Mechanical & Materials Engineering, University of Cincinnati, Cincinnati, 45221, OH, United States | I41: Digital twin; Industrial Internet of Things; Large language model; Multi-agent framework; Retrieval-augmented generation | J41: =IF(OR( E41="International Journal of Production Research", E41="Journal of Manufacturing Technology Management", E41="International Journal of Production Economics", E41="Journal of Industrial Information Integration", E41="Transportation Research Part E: Logistics and Transportation Review", E41="Journal of Cleaner Production", E41="MM 2024 - Proceedings of the 32nd ACM International Conference on Multimedia", E41="Oeconomia Copernicana", E41="Technology in Society" ), "MGT", "ENG") -> ENG | K41: empirical | L41: Design science research | M41: Techniques | N41: Manufacturing | O41: process monitoring; fault diagnosis; maintenance; Work instructions for operators (task Q&A) | R41: LLM enabled digital twin; LLM agents | S41: the llmdt sys accesses/standardizes realtime legacy+smart machine data w/MTConnect;retrieves unstructured knowlege w/rag,+provides diagnoses+control;fine tunw supervisor improved classification,+experiments showed accurate Q&A plus successful closed loop 3Dprinter corrections w/ | T41: delivers contextaware guidance w/o manual lookups;accelerates troubleshooting;improve part qual,+supports humancentric interaction through dt avatar+NL interface | U41: mtconnect standardization of heterogeneous devices | V41: integrating legacy equipment at scale;maintaining realtime;contextaccurate responce;fine tunning cost/effort | W41: Enhance — Retrieves manuals and fault logs via RAG, standardizes IIoT streams, aggregates knowledge context for diagnosis. Decide — Diagnoses anomalies using real-time sensors and knowledge base, recommending corrective actions and parameters to operators. Act — Parses natural-language commands to execute machine-control functions, updating printer parameters and positions in real-time safely. | X41: multiagent llm fw integrated w/IIoT/MTConnect dt;fine tunw gpt4omini supervisor using synthetic labeled dataset;hybrid rag for machine expertise | Y41: multi-agent LLM framework integrated into DT | Z41: 4 | AA41: 3 | AB41: Lab validation | AC41: Integration component testing | AD41: Assistive GenAI | AE41: Y | AG41: The multi-agent LLM is integrated with an IIoT platform and digital twin, streaming real-time data from legacy panels and 3D printers in a university testbed. Demonstration remains in a controlled lab, not a production facility. | AH41: Agents interpret IIoT data, visualize states, and provide expert-like recommendations and fault insights. They support operators via a digital-twin “virtual expert” but don’t autonomously change machine settings or control production. | AK41: {=_xlfn.IFS(AC41="Principles observation",1, AC41="Concept formulation",2, AC41="Proof-of-concept simulation", 3, AC41="Core function validation", 4, AC41="Integration component testing", 5, AC41="Component validation in relevant environment", 6, AC41="Subsystem demonstration in relevant environment", 7, AC41="System demonstration in operational environment", 8, AC41="Production qualification", 9, AC41="Mission-proven operations", 10)} -> 5 | AL41: {=_xlfn.IFS(AD41="Assistive GenAI", 1, AD41="GenAI-led with human oversight", 2, AD41="Autonomous process learning", 3)} -> 1
A42: 44 | B42: A five-dimensional digital twin framework driven by large language models-enhanced RL for CNC systems | C42: Lin X.; Chen W.; Zhou Z.; Li J.; Zhao Y.; Zhang X. | D42: 2025 | E42: Robotics and Computer-Integrated Manufacturing | F42: 1 | G42: =IFERROR(LEFT(C42, FIND(";", C42) - 1), C42) -> Lin X. | H42: Shenyang Institute of Computing Technology, Chinese Academy of Sciences, Shenyang, 110168, China | I42: CNC system; Digital twin; Large language models; Reinforcement learning | J42: =IF(OR( E42="International Journal of Production Research", E42="Journal of Manufacturing Technology Management", E42="International Journal of Production Economics", E42="Journal of Industrial Information Integration", E42="Transportation Research Part E: Logistics and Transportation Review", E42="Journal of Cleaner Production", E42="MM 2024 - Proceedings of the 32nd ACM International Conference on Multimedia", E42="Oeconomia Copernicana", E42="Technology in Society" ), "MGT", "ENG") -> ENG | K42: empirical | L42: Design science research | M42: Techniques | N42: Manufacturing | O42: Process planning | P42: Machinery | R42: LLM enabled digital twin | S42: the llm serves as indirect decisionmaker within rl;integrating llmenhanced rl into dt fw reduce toolaxis vector variation+decreases collision interference;validating approach for CNC sys | T42: improve toolpath stability+machining safe/qual by guiding rl toward lowvariation;collisionavoiding trajectories within dt | V42: heterogeneous CNC protocols risk data distortion;llm+RL industrial deployment nascent;training stability/compute constaints need careful normalization+parameterefficent tuning | W42: Enhance — Analyzes historical/trajectory data to provide decision references and environment-aligned action probabilities for RL . Decide — Generates and scores candidate actions to guide RL toward safer, low-variation tool-axis trajectories | X42: loRA parameterefficent fine tunning adapts it to machining prompts state → action candidates:At every step llm;surface normal/curvature;limits;recent path smoothness | Y42: LoRA fine-tuned LLM for CNC axis direction planner | Z42: 4 | AA42: 3 | AB42: Lab validation | AC42: Integration component testing | AD42: GenAI-led with human oversight | AE42: Y | AG42: LLM-enhanced RL planner runs inside a CNC digital twin, linked to real CNC data via OPC UA. Tool-axis planning is trained and evaluated in virtual machining, validating integrated components and data flows, not production pilots. | AH42: In the twin, LLM+RL autonomously chooses tool-axis vector actions and trajectories. Humans define objectives, prompts, and constraints and would review or approve generated NC programs before real execution, implying GenAI-led planning under human supervision. | AK42: {=_xlfn.IFS(AC42="Principles observation",1, AC42="Concept formulation",2, AC42="Proof-of-concept simulation", 3, AC42="Core function validation", 4, AC42="Integration component testing", 5, AC42="Component validation in relevant environment", 6, AC42="Subsystem demonstration in relevant environment", 7, AC42="System demonstration in operational environment", 8, AC42="Production qualification", 9, AC42="Mission-proven operations", 10)} -> 5 | AL42: {=_xlfn.IFS(AD42="Assistive GenAI", 1, AD42="GenAI-led with human oversight", 2, AD42="Autonomous process learning", 3)} -> 2
A43: 45 | B43: LLM-Enhanced Human-Machine Interaction for Adaptive Decision-Making in Dynamic Manufacturing Process Environments | C43: Keskin Z.; Joosten D.; Klasen N.; Huber M.; Liu C.; Drescher B.; Schmitt R.H. | D43: 2025 | E43: IEEE Access | F43: 1 | G43: =IFERROR(LEFT(C43, FIND(";", C43) - 1), C43) -> Keskin Z. | H43: INC Innovation Center GmbH, Munich, 81539, Germany | I43: anomaly detection; data visualization; data-driven decision-making; Industry 4.0; large language models (LLMs); manufacturing; natural language queries; production process optimization; real-time sensor data; shop floor analytics | J43: =IF(OR( E43="International Journal of Production Research", E43="Journal of Manufacturing Technology Management", E43="International Journal of Production Economics", E43="Journal of Industrial Information Integration", E43="Transportation Research Part E: Logistics and Transportation Review", E43="Journal of Cleaner Production", E43="MM 2024 - Proceedings of the 32nd ACM International Conference on Multimedia", E43="Oeconomia Copernicana", E43="Technology in Society" ), "MGT", "ENG") -> ENG | K43: empirical | L43: Design science research | M43: Applications | N43: Manufacturing | O43: process monitoring; fault diagnosis | P43: Machinery | R43: LLM agents | S43: the llm assistant retrieves correct data+gen tailored visualizations from NL prompts;in 8/10 trials it produced correct SQL+results | T43: llmdriven data exploration reduce reliance on analysts;speeds anomaly investigation,+eases access to complex shopfloor data w/NL queries+flexibel visualizations | U43: structured ISA95derived schema;UNScompatible data ingestion | V43: acc/reliabilty gaps 2/10 prompts incorrect;domian customization/fine tunning needs;integr/scale+dataprotection concerns;improved error handling+knowlege grounding required | W43: Enhance: schema-aware NL2SQL converts natural prompts into queries with joins, aggregations, filters; a code agent auto-generates Python plots. Decide: the LLM selects features, composes anomaly-centric analyses, highlights deviations, recommends comparisons/time windows, and surfaces diagnostic slices. | X43: modular agents orchestrated w/LangGraph:1;llm orchestrator:A gpt4omini agent built w/LangGraph/LangChain decides;2;The SQLAgent:turns naturla language prompt into schemaaware SQL joins | Y43: multi-agent LLM enhances access (NL→SQL + auto-plots) and decides by generating task-specific analyses/visuals that help operators investigate anomalies quickly | Z43: 4 | AA43: 3 | AB43: Lab validation | AC43: Core function validation | AD43: Assistive GenAI | AE43: Y | AG43: The architecture and LLM-driven HMI are tested on historical and augmented data from an industrial extrusion process. The focus is on querying and visualization; there is no evidence of deployment in an online production environment. | AH43: The LLM interprets natural-language queries and produces tailored visualizations and analytics, supporting operators’ decisions. It does not autonomously adjust process parameters or execute control actions; humans retain full authority over interventions. | AK43: {=_xlfn.IFS(AC43="Principles observation",1, AC43="Concept formulation",2, AC43="Proof-of-concept simulation", 3, AC43="Core function validation", 4, AC43="Integration component testing", 5, AC43="Component validation in relevant environment", 6, AC43="Subsystem demonstration in relevant environment", 7, AC43="System demonstration in operational environment", 8, AC43="Production qualification", 9, AC43="Mission-proven operations", 10)} -> 4 | AL43: {=_xlfn.IFS(AD43="Assistive GenAI", 1, AD43="GenAI-led with human oversight", 2, AD43="Autonomous process learning", 3)} -> 1
A44: 46 | B44: A Generative AI approach to improve in-situ vision tool wear monitoring with scarce data | C44: Garcia-Perez A.; Gomez-Silva M.J.; de la Escalera-Hueso A. | D44: 2025 | E44: Journal of Intelligent Manufacturing | F44: 1 | G44: =IFERROR(LEFT(C44, FIND(";", C44) - 1), C44) -> Garcia-Perez A. | H44: Simulation Systems, ITP Aero, Francisca Delgado 9, Madrid, Alcobendas, Spain | I44: Computer Vision; GAN; Generative Artificial Intelligence (AI); Neural Networks; Stable Diffusion; Tool Condition Monitoring (TCM); Tool wear; Vertical lathe; Vision Transformers (ViT) | J44: =IF(OR( E44="International Journal of Production Research", E44="Journal of Manufacturing Technology Management", E44="International Journal of Production Economics", E44="Journal of Industrial Information Integration", E44="Transportation Research Part E: Logistics and Transportation Review", E44="Journal of Cleaner Production", E44="MM 2024 - Proceedings of the 32nd ACM International Conference on Multimedia", E44="Oeconomia Copernicana", E44="Technology in Society" ), "MGT", "ENG") -> ENG | K44: empirical | L44: Design science research | M44: Techniques | N44: Manufacturing | O44: quality management/inspection | P44: Aerospace | R44: data augmentation | S44: genai made new;realistic toolwear images to pad tiny;imbalanced datasets;These synthetic pictures boosted inspectors acc from 80% to 96% | T44: genai mitigates scarce/imbalanced data;producing realistic toolwear images | V44: gan training cost;dependency on image qual | W44: Enhance — Generates and curates synthetic tool-wear images to enrich scarce datasets and improve classifier reliability | X44: 2 architectures:GANs SCWGANGP & diffusion modles FSD SCWGANGP fast;classaware image maker;FSD higherfidelity;classconditioned diffusion | Y44: tool image augmentation--> better training of DL algo for quality inspection of tool inserts for machining process | Z44: 4 | AA44: 3 | AB44: Lab validation | AC44: Core function validation | AD44: Assistive GenAI | AE44: Y | AG44: Industrial images from a real vertical lathe are collected, augmented with GAN-based synthetic views, and used to train and evaluate a deep tool-wear classifier offline; no closed-loop control or deployment. | AH44: GANs generate additional tool images to train the classifier, which outputs condition labels to support inspectors or monitoring software; humans or conventional systems still decide tool changes and actions. | AK44: {=_xlfn.IFS(AC44="Principles observation",1, AC44="Concept formulation",2, AC44="Proof-of-concept simulation", 3, AC44="Core function validation", 4, AC44="Integration component testing", 5, AC44="Component validation in relevant environment", 6, AC44="Subsystem demonstration in relevant environment", 7, AC44="System demonstration in operational environment", 8, AC44="Production qualification", 9, AC44="Mission-proven operations", 10)} -> 4 | AL44: {=_xlfn.IFS(AD44="Assistive GenAI", 1, AD44="GenAI-led with human oversight", 2, AD44="Autonomous process learning", 3)} -> 1
A45: 47 | B45: OmEGa(Ω): Ontology-based information extraction framework for constructing task-centric knowledge graph from manufacturing documents with large language model | C45: Shim M.; Choi H.; Koo H.; Um K.; Lee K.-H.; Lee S. | D45: 2025 | E45: Advanced Engineering Informatics | F45: 1 | G45: =IFERROR(LEFT(C45, FIND(";", C45) - 1), C45) -> Shim M. | H45: Department of Computer Science, Yonsei University, 50 Yonsei-ro, Sedaemun-gu, Seoul, 03722, South Korea | I45: Document understanding; Information extraction; Knowledge graph; Large language model; Manufacturing and maintenance process; Ontology modeling | J45: =IF(OR( E45="International Journal of Production Research", E45="Journal of Manufacturing Technology Management", E45="International Journal of Production Economics", E45="Journal of Industrial Information Integration", E45="Transportation Research Part E: Logistics and Transportation Review", E45="Journal of Cleaner Production", E45="MM 2024 - Proceedings of the 32nd ACM International Conference on Multimedia", E45="Oeconomia Copernicana", E45="Technology in Society" ), "MGT", "ENG") -> ENG | K45: empirical | L45: Design science research | M45: Techniques | N45: Manufacturing | O45: Work instructions for operators (task Q&A) | P45: automotive | R45: LLM enabled KG | S45: using ontologyguided;multimodal llm pipeline;OmEGa extracts task;location | T45: genai structures messy multimodal manuals into taskcentric kg+enable kgQA | U45: taskCentric Ontology TCO w/rules/constaints;humaninloop vaild | V45: structural:abbreviations;scattered multimodal content;Contextual:PLMdomian mismatch;scarce labeled docs | W45: Enhance — LLMs extract and structure multimodal manufacturing knowledge into task-centric ontologies and graphs for reliable reuse | X45: loRA fine tunw llama performs instance recognition+relation classification on multimodal documents NER/RE | Y45: using LLM to construct a KG (NER) | Z45: 4 | AA45: 3 | AB45: Lab validation | AC45: Core function validation | AD45: Assistive GenAI | AE45: Y | AG45: Develops and evaluates an ontology-driven information extraction pipeline using LLMs on curated manufacturing documents with annotated ground truth; prototype runs on datasets only, not integrated with live shop-floor systems. | AH45: LLM extracts entities and relations to build a task-centric knowledge graph, enriching documentation and search; it does not autonomously schedule, control, or modify manufacturing processes. | AK45: {=_xlfn.IFS(AC45="Principles observation",1, AC45="Concept formulation",2, AC45="Proof-of-concept simulation", 3, AC45="Core function validation", 4, AC45="Integration component testing", 5, AC45="Component validation in relevant environment", 6, AC45="Subsystem demonstration in relevant environment", 7, AC45="System demonstration in operational environment", 8, AC45="Production qualification", 9, AC45="Mission-proven operations", 10)} -> 4 | AL45: {=_xlfn.IFS(AD45="Assistive GenAI", 1, AD45="GenAI-led with human oversight", 2, AD45="Autonomous process learning", 3)} -> 1
A46: 48 | B46: OC-HMAS: Dynamic Self-Organization and Self-Correction in Heterogeneous Multiagent Systems Using Multimodal Large Models | C46: Feng P.; Yang T.; Liang M.; Wang L.; Gao Y. | D46: 2025 | E46: IEEE Internet of Things Journal | F46: 1 | G46: =IFERROR(LEFT(C46, FIND(";", C46) - 1), C46) -> Feng P. | H46: Dalian Maritime University, School of Navigation, Dalian, 116026, China | I46: Embodied intelligence; environmental perception; Internet of Things (IoT); large language model (LLM); multiagent system (MAS); task scheduling; vision language model (VLM) | J46: =IF(OR( E46="International Journal of Production Research", E46="Journal of Manufacturing Technology Management", E46="International Journal of Production Economics", E46="Journal of Industrial Information Integration", E46="Transportation Research Part E: Logistics and Transportation Review", E46="Journal of Cleaner Production", E46="MM 2024 - Proceedings of the 32nd ACM International Conference on Multimedia", E46="Oeconomia Copernicana", E46="Technology in Society" ), "MGT", "ENG") -> ENG | K46: empirical | L46: Design science research | M46: Techniques | N46: Supply Chain | O46: human-robot collaboration; Logistics planning | R46: LLM agents | S46: multimodal vlm+llm planing delivers higher task success+faster completion;validating dynamic selforganization+selfcorrection in IoT settings | T46: genai enable contextaware planing+rapid replanning from multimodal cues;improving eff;safe,+scalability for logistics/inspection/rescue missions under uncertainity | U46: multimodal sensing RGB;InstanceSeg;LiDar;hybrid cloudedge deployment,+robust comms 5G/WiFi 6 | V46: centralized modles can add latency | W46: Enhance — Fuses RGB/InstanceSeg/LiDAR into rich scene descriptions that standardize context for planning; Decide — Decomposes tasks, assigns roles, and plans safe, efficient routes adaptively in real time (15). Act — Issues updated control intents that trigger path replans and agent actions during self-correction | X46: multimodal llm/vlm agents for perception→planing;llmenabled task decomposition/role allocation;vlm scene understanding;kgfree ragstyle fusion of multimodal descriptors | Y46: the LLM is the planner/orchestrator—it turns mission text + grounded visual cues into who does what, where, and when, and keeps fixing the plan as the environment changes. | Z46: 4 | AA46: 2 | AB46: Concept | AC46: Proof-of-concept simulation | AD46: Autonomous process learning | AE46: Y | AG46: OC-HMAS is validated through simulation-based logistics, inspection, and rescue scenarios using multimodal synthetic sensor data and simulated agents, demonstrating coordination benefits without connecting to physical robots or real production assets. | AH46: Central planner and agents use multimodal LLM/VLM reasoning to self-organize, allocate tasks, and adapt strategies end-to-end after receiving a high-level goal, with no routine human approvals in the loop. | AK46: {=_xlfn.IFS(AC46="Principles observation",1, AC46="Concept formulation",2, AC46="Proof-of-concept simulation", 3, AC46="Core function validation", 4, AC46="Integration component testing", 5, AC46="Component validation in relevant environment", 6, AC46="Subsystem demonstration in relevant environment", 7, AC46="System demonstration in operational environment", 8, AC46="Production qualification", 9, AC46="Mission-proven operations", 10)} -> 3 | AL46: {=_xlfn.IFS(AD46="Assistive GenAI", 1, AD46="GenAI-led with human oversight", 2, AD46="Autonomous process learning", 3)} -> 3
A47: 49 | B47: Enhancing retrieval-augmented generation for interoperable industrial knowledge representation and inference toward cognitive digital twins | C47: Shi D.; Li J.; Meyer O.; Bauernhansl T. | D47: 2025 | E47: Computers in Industry | F47: 0 | G47: =IFERROR(LEFT(C47, FIND(";", C47) - 1), C47) -> Shi D. | H47: Fraunhofer Institute for Manufacturing Engineering and Automation IPA, Nobelstraße 12, Stuttgart, 70569, Germany | I47: Asset administration shell; Digital twin; Entity matching; Large language model; Retrieval-augmented generation | J47: =IF(OR( E47="International Journal of Production Research", E47="Journal of Manufacturing Technology Management", E47="International Journal of Production Economics", E47="Journal of Industrial Information Integration", E47="Transportation Research Part E: Logistics and Transportation Review", E47="Journal of Cleaner Production", E47="MM 2024 - Proceedings of the 32nd ACM International Conference on Multimedia", E47="Oeconomia Copernicana", E47="Technology in Society" ), "MGT", "ENG") -> ENG | K47: empirical | L47: Design science research | M47: Techniques | O47: Digital twin architecture design | P47: Machinery | R47: LLM enabled digital twin | S47: encoding AAS entities+adding CSLfine tunw llm reranker markedly improve retrieval+answers of rag | T47: the enhanced rag yields more correct+complete integr answers;reduce manual crossdocument effort,+supports interoperable Cdt development across tools/organizations | V47: reranking adds latency;need robust domian adaptation+safe deployment at scale | W47: Enhance — Encodes AAS entities and reranks candidates with CSL-finetuned LLM, improving retrieval robustness and answer correctness | X47: advanced rag w/llm reranker CSLfine tunw mistral7B for robotic work cell integr into dt | Y47: an advanced RAG for better retrieval | Z47: 4 | AA47: 3 | AB47: Lab validation | AC47: Core function validation | AD47: Assistive GenAI | AE47: N | AF47: Lab validation – Integration component testing | AG47: Implements an enhanced RAG pipeline over AAS-based knowledge, fine-tuned reranker, and ROS-based robotic cell CDT; validated via engineer queries and retrieval metrics in a demonstrator, not an operational factory. | AH47: LLM-based RAG answers engineering questions about kinematic models and integration details, supporting human system integrators; it never autonomously reconfigures robots or executes control actions. | AK47: {=_xlfn.IFS(AC47="Principles observation",1, AC47="Concept formulation",2, AC47="Proof-of-concept simulation", 3, AC47="Core function validation", 4, AC47="Integration component testing", 5, AC47="Component validation in relevant environment", 6, AC47="Subsystem demonstration in relevant environment", 7, AC47="System demonstration in operational environment", 8, AC47="Production qualification", 9, AC47="Mission-proven operations", 10)} -> 4 | AL47: {=_xlfn.IFS(AD47="Assistive GenAI", 1, AD47="GenAI-led with human oversight", 2, AD47="Autonomous process learning", 3)} -> 1
A48: 51 | B48: A knowledge-graph enhanced large language model-based fault diagnostic reasoning and maintenance decision support pipeline towards industry 5.0 | C48: Ma Y.; Zheng S.; Yang Z.; Pan H.; Hong J. | D48: 2025 | E48: International Journal of Production Research | F48: 0 | G48: =IFERROR(LEFT(C48, FIND(";", C48) - 1), C48) -> Ma Y. | H48: School of Software Engineering, Xi'an Jiaotong University, Xi'an, China | I48: Domain-specific large language models; fault diagnostic reasoning; industry 5.0; knowledge graph; mechanical equipment | J48: ENG | K48: empirical | L48: Design science research | M48: Techniques | N48: Manufacturing | O48: fault diagnosis; maintenance | P48: Machinery | R48: KG‑augmented LLM | S48: kgenhanced llm beat vanilla llms+rag baselines on fault diag & maint Q&A evaluation dataset;Subgraph correction+web search further improve robustness | T48: the kgguided llm reduce hallucinations;improve diagnostic reliabilty+completeness,+makes fault reasoning accessible w/NL;supporting humancentric maint in Industry 5.0 | V48: perf depends on kg coverage/qual;multiple llm calls add server burden;remaining hallucination risk;proprietary modles raise privacy concerns | W48: Enhance — Structures and retrieves precise KG subgraphs, aligning free-text faults to reliable domain knowledge. Decide — Synthesises subgraph evidence to reason root causes and propose maintenance guidance from symptoms. | X48: compared gpt3.5;gpt4;chatglm3;Yi34B | Y48: KG-enhanced LLM for fault diagnosis & maintenance for cranes | Z48: 4 | AA48: 4 | AB48: Lab validation | AC48: Core function validation | AD48: Assistive GenAI | AE48: Y | AG48: They design an FDRKG-LLM pipeline and evaluate it on a self-constructed fault diagnosis database with offline metrics; no live connection to plant systems or deployment, so it is lab-scale functional validation only. | AH48: The LLM+KG pipeline analyzes fault descriptions and suggests diagnostic reasoning and maintenance guidance; humans remain responsible for interpreting recommendations and executing maintenance actions, so GenAI acts as an assistive copilot. | AK48: {=_xlfn.IFS(AC48="Principles observation",1, AC48="Concept formulation",2, AC48="Proof-of-concept simulation", 3, AC48="Core function validation", 4, AC48="Integration component testing", 5, AC48="Component validation in relevant environment", 6, AC48="Subsystem demonstration in relevant environment", 7, AC48="System demonstration in operational environment", 8, AC48="Production qualification", 9, AC48="Mission-proven operations", 10)} -> 4 | AL48: {=_xlfn.IFS(AD48="Assistive GenAI", 1, AD48="GenAI-led with human oversight", 2, AD48="Autonomous process learning", 3)} -> 1
A49: 52 | B49: Toward Cognitive Digital Twin System of Human–Robot Collaboration Manipulation | C49: Li X.; He B.; Wang Z.; Zhou Y.; Li G.; Li X. | D49: 2025 | E49: IEEE Transactions on Automation Science and Engineering | F49: 0 | G49: =IFERROR(LEFT(C49, FIND(";", C49) - 1), C49) -> Li X. | H49: The College of Electronics and Information Engineering, Shanghai Research Institute for Intelligent Autonomous Systems, the National Key Laboratory of Autonomous Intelligent Unmanned Systems, The Frontiers Science Center for Intelligent Autonomous Systems, Tongji University, Shanghai, 201804, China | I49: digital twin; Human-robot collaboration; large language models; multielement decision-making; scene semantic graph | J49: =IF(OR( E49="International Journal of Production Research", E49="Journal of Manufacturing Technology Management", E49="International Journal of Production Economics", E49="Journal of Industrial Information Integration", E49="Transportation Research Part E: Logistics and Transportation Review", E49="Journal of Cleaner Production", E49="MM 2024 - Proceedings of the 32nd ACM International Conference on Multimedia", E49="Oeconomia Copernicana", E49="Technology in Society" ), "MGT", "ENG") -> ENG | K49: empirical | L49: Design science research | M49: Techniques | N49: Manufacturing | O49: human-robot collaboration | R49: LLM enabled digital twin | S49: merging HRCSSG semantics+activity priors into prompts enable gpt4 to plan tasks;detect anomalies,+reason schedules;volunteerrated acc >92% for AD/SR+73% for TP;sys tracks human/robot positions ≈18.5 mm/7.3 mm+sustains 16 vps semantic inference | T49: provides professional;comprehensible guidance to op;monitors safe/standardization,+supports robust multielement decisions for flexibel HRC in dynamic scenes | V49: simple lab scenes w/fixed entities;singlecamera limits+occlusions;variability across llm outputs | W49: Decide — Generates task plans, anomaly flags, and schedule reasoning from semantic graph and priors to guide operators | X49: gpt4 decision engine w/structured prompts grounded in scene semantic graph & task priors | Y49: integrate scene semantics with prior knowledge of activities into a prompt for GPT-4, for robotic task planning | Z49: 4 | AA49: 3 | AB49: Lab validation | AC49: Component validation in relevant environment | AD49: GenAI-led with human oversight | AE49: Y | AG49: HRC-CogiDT integrates LLMs with a digital twin, perception modules, and a real collaborative robot platform; experiments run on a laboratory HRC cell, validating multi-component interaction and decision pipelines, not industrial deployment. | AH49: The system uses LLM-driven reasoning for task planning, anomaly detection, and schedule reasoning, while human operators collaborate and monitor safety, implying LLM-led decisions with humans supervising and intervening when necessary. | AK49: {=_xlfn.IFS(AC49="Principles observation",1, AC49="Concept formulation",2, AC49="Proof-of-concept simulation", 3, AC49="Core function validation", 4, AC49="Integration component testing", 5, AC49="Component validation in relevant environment", 6, AC49="Subsystem demonstration in relevant environment", 7, AC49="System demonstration in operational environment", 8, AC49="Production qualification", 9, AC49="Mission-proven operations", 10)} -> 6 | AL49: {=_xlfn.IFS(AD49="Assistive GenAI", 1, AD49="GenAI-led with human oversight", 2, AD49="Autonomous process learning", 3)} -> 2
A50: 53 | B50: Human-LLM collaboration in generative design for customization | C50: Wang X.; Jiang Z.; Xiong Y.; Liu A. | D50: 2025 | E50: Journal of Manufacturing Systems | F50: 0 | G50: =IFERROR(LEFT(C50, FIND(";", C50) - 1), C50) -> Wang X. | H50: School of System Design and Intelligent Manufacturing, Southern University of Science and Technology, Shenzhen, 518055, China | I50: Collaborative design; Customization; Generative design; Knowledge-based system; Large language models | J50: =IF(OR( E50="International Journal of Production Research", E50="Journal of Manufacturing Technology Management", E50="International Journal of Production Economics", E50="Journal of Industrial Information Integration", E50="Transportation Research Part E: Logistics and Transportation Review", E50="Journal of Cleaner Production", E50="MM 2024 - Proceedings of the 32nd ACM International Conference on Multimedia", E50="Oeconomia Copernicana", E50="Technology in Society" ), "MGT", "ENG") -> ENG | K50: empirical | L50: Conceptual development + case study | M50: Strategy | N50: Design | O50: Generative design | P50: automotive | R50: LLM chatbot | S50: the defines llm roles producer/provider/decisionmaker+methodselection flow;then show in proactive case;perf holds for ≤4 objectives | T50: llms lower expertise barriers;speed customization,+align designs w/shopspecific mfg constaints;enabling customers w/minimal GDfC knowlege to obtain vaild;manufacturable options w/clearer explanations | U50: data & knowlege:designmfg kg encoding constaints;Tech patterns:fine tunning gpt3.5turbo0613 for style/terminology+rag for dynamic constaints;proc:front/backend orchestrating external generative tools+code prompts;Governance:constrain search to kg+limit objectives ≤4 to curb hallucination | V50: acc drops when many objectives requested;knowlege base scope limits coverage;resorces constaints+remaining hallucination risk demand expert oversight | W50: Enhance — Maps vague intentions to structured specs and retrieves constraints from knowledge graph for manufacturability assurance. Decide — Generates commands, compares design alternatives, and recommends manufacturable options under stated criteria with explanation transparency | X50: fine tunw gpt3.5;rag over designmfg kg;prompttocode orchestration backend interface | Y50: a flow how to select LLM (finetune/RAG/prompts) for design. Then a case in vintage vehicle interior trim customization | Z50: 4 | AA50: 3 | AB50: Concept | AC50: Concept formulation | AD50: Assistive GenAI | AE50: Y | AG50: The paper conceptualizes human-LLM collaboration schemes and a process framework for generative design, illustrated by a vehicle interior customization case, but presents no implemented software prototype, datasets, or quantitative experiments. | AH50: LLMs are positioned as collaborators that generate design options, translate problem definitions, and support evaluation, while designers and customers make final decisions and control tools, so GenAI remains primarily assistive. | AK50: {=_xlfn.IFS(AC50="Principles observation",1, AC50="Concept formulation",2, AC50="Proof-of-concept simulation", 3, AC50="Core function validation", 4, AC50="Integration component testing", 5, AC50="Component validation in relevant environment", 6, AC50="Subsystem demonstration in relevant environment", 7, AC50="System demonstration in operational environment", 8, AC50="Production qualification", 9, AC50="Mission-proven operations", 10)} -> 2 | AL50: {=_xlfn.IFS(AD50="Assistive GenAI", 1, AD50="GenAI-led with human oversight", 2, AD50="Autonomous process learning", 3)} -> 1
A51: 54 | B51: Integrating Graph Retrieval-Augmented Generation With Large Language Models for Supplier Discovery | C51: Li Y.; Ko H.; Ameri F. | D51: 2025 | E51: Journal of Computing and Information Science in Engineering | F51: 0 | G51: =IFERROR(LEFT(C51, FIND(";", C51) - 1), C51) -> Li Y. | H51: School of Manufacturing Systems and Networks, Arizona State University, Mesa, 85212, AZ, United States | I51: artificial intelligence; big data and analytics; cybermanufacturing; data-driven engineering; knowledge engineering; machine learning for engineering applications; manufacturing automation | J51: =IF(OR( E51="International Journal of Production Research", E51="Journal of Manufacturing Technology Management", E51="International Journal of Production Economics", E51="Journal of Industrial Information Integration", E51="Transportation Research Part E: Logistics and Transportation Review", E51="Journal of Cleaner Production", E51="MM 2024 - Proceedings of the 32nd ACM International Conference on Multimedia", E51="Oeconomia Copernicana", E51="Technology in Society" ), "MGT", "ENG") -> ENG | K51: empirical | L51: Design science research | M51: Techniques | N51: Supply Chain | O51: supplier identification | R51: LLM enabled KG; KG‑augmented LLM | S51: fine tunning gpt3.5 markedly improve supplier triplet extraction over base modle in graph construction;Neo4j suppliercapability kg plus Graphrag yields higher precision/F1/acc than SummaryIndex+KnowledgeGraphIndex in Q&A;built SCkg spans 1663 entities+6911 relationships | T51: sckgrag improve supplier visibility+findability;producing more precise;explainable answers+helping supply managers identify qualified SMMs faster w/fewer mismatches | U51: data & knowlege:SUDOKN ontology+MCT thesaurus | V51: perf depends on supplier data qual;need more diverse data+adaptive/semisupervised extraction;SME labeling cost;generalization across domains remains open task | W51: Enhance — Transforms messy supplier webpages into standardized knowledge graph using ontology-guided extraction and normalization for discovery. Decide — Answers complex sourcing queries by retrieving subgraphs and synthesizing evidence to support supplier selection decisions. | X51: fine tunw gpt3.5 extractor for graph construction;Graph rag | Y51: KG-RAG for supplier identification | Z51: 4 | AA51: 3 | AB51: Lab validation | AC51: Core function validation | AD51: Assistive GenAI | AE51: Y | AG51: They build an ontology-driven supplier capability knowledge graph and integrate it with LLM-based RAG, evaluating answer quality and retrieval metrics on real supplier data, but only as an offline case study without enterprise integration. | AH51: The system retrieves and generates richer supplier information in response to natural-language queries, but users still select suppliers and act on recommendations; GenAI augments search and analysis rather than automating procurement decisions. | AK51: {=_xlfn.IFS(AC51="Principles observation",1, AC51="Concept formulation",2, AC51="Proof-of-concept simulation", 3, AC51="Core function validation", 4, AC51="Integration component testing", 5, AC51="Component validation in relevant environment", 6, AC51="Subsystem demonstration in relevant environment", 7, AC51="System demonstration in operational environment", 8, AC51="Production qualification", 9, AC51="Mission-proven operations", 10)} -> 4 | AL51: {=_xlfn.IFS(AD51="Assistive GenAI", 1, AD51="GenAI-led with human oversight", 2, AD51="Autonomous process learning", 3)} -> 1
A52: 55 | B52: Embodied Intelligence Empowering Customized Manufacturing: Architecture, Opportunities, and Challenges | C52: Tan J.; Shi J.; Wu L.; Chen B.; Tang H.; Zhang C.; Zhang W.; Wan J.; Wang S. | D52: 2025 | E52: IEEE Access | F52: 0 | G52: =IFERROR(LEFT(C52, FIND(";", C52) - 1), C52) -> Tan J. | H52: South China University of Technology, School of Mechanical and Automotive Engineering, Guangzhou, 510641, China | I52: Collaborative Reasoning; Customized Manufacturing; Embodied Intelligence; Embodied Manufacturing; Model Fusion; Multi-Source Perception | J52: =IF(OR( E52="International Journal of Production Research", E52="Journal of Manufacturing Technology Management", E52="International Journal of Production Economics", E52="Journal of Industrial Information Integration", E52="Transportation Research Part E: Logistics and Transportation Review", E52="Journal of Cleaner Production", E52="MM 2024 - Proceedings of the 32nd ACM International Conference on Multimedia", E52="Oeconomia Copernicana", E52="Technology in Society" ), "MGT", "ENG") -> ENG | K52: empirical | L52: Conceptual development + case study | M52: Strategy | N52: Manufacturing | O52: customized manufacturing | Q52: Embodied Intelligence (EI) concept | R52: LLM chatbot | S52: propose CEIM to fuse multisource perception+ai modle outputs;show;w/giftbox line;how llms analyze logs | T52: llms improve semantic integr+coordination across IoMT;equipment,+resorces;enabling more flexibel planing;quicker anomaly responce,+humanstyle interactive management in customized mfg | V52: ei in CM faces multisensor fusion+semantic misalignment;data integr at scale;precise motion control;compute/training demands | W52: Enhance — Unifies logs/AI outputs via semantics; LLMs fuse knowledge to enrich shared context. Decide — Reasons over cross-element signals to schedule tasks and adjust throughput in real time. Act — Generates management instructions that update device parameters and operational states across the line | Y52: very conceptual and abstract, the use of LLM: enhance semantic fusion of multi-source data, decide on scheduling/adjustments from fused evidence, and act by issuing management instructions to equipment | Z52: 4 | AA52: 3 | AB52: Concept | AC52: Principles observation | AD52: Autonomous process learning | AE52: Y | AG52: This is a survey and conceptual architecture paper on embodied intelligence for customized manufacturing, synthesizing prior work and proposing future EI system structures, without implementing or empirically validating a concrete GenAI system. | AH52: The envisioned embodied-intelligence architecture targets closed-loop perception, learning, and control for multi-agent customized manufacturing, with humans setting objectives while EI agents autonomously optimize scheduling and operations over time. | AK52: {=_xlfn.IFS(AC52="Principles observation",1, AC52="Concept formulation",2, AC52="Proof-of-concept simulation", 3, AC52="Core function validation", 4, AC52="Integration component testing", 5, AC52="Component validation in relevant environment", 6, AC52="Subsystem demonstration in relevant environment", 7, AC52="System demonstration in operational environment", 8, AC52="Production qualification", 9, AC52="Mission-proven operations", 10)} -> 1 | AL52: {=_xlfn.IFS(AD52="Assistive GenAI", 1, AD52="GenAI-led with human oversight", 2, AD52="Autonomous process learning", 3)} -> 3
A53: 57 | B53: Learning packing-and-unpacking synergistic policy via LLM-guided DRL for robust online robotic packing | C53: Yang S.; Song S.; Song R.; Cheng J.; Li Y.; Zhang W. | D53: 2025 | E53: Advanced Engineering Informatics | F53: 0 | G53: =IFERROR(LEFT(C53, FIND(";", C53) - 1), C53) -> Yang S. | H53: Department of Urology, Qilu Hospital of Shandong University, Jinan, China | I53: Deep reinforcement learning; Large Language Model; Online 3D-BPP; Robotic packing; Warehouse Automation | J53: =IF(OR( E53="International Journal of Production Research", E53="Journal of Manufacturing Technology Management", E53="International Journal of Production Economics", E53="Journal of Industrial Information Integration", E53="Transportation Research Part E: Logistics and Transportation Review", E53="Journal of Cleaner Production", E53="MM 2024 - Proceedings of the 32nd ACM International Conference on Multimedia", E53="Oeconomia Copernicana", E53="Technology in Society" ), "MGT", "ENG") -> ENG | K53: empirical | L53: Design science research | M53: Techniques | N53: Supply Chain | O53: Logistics planning | R53: LLM chatbot | S53: llmguided heuristics+DRL learns synergistic packingunpacking policies;space utilization rises w/higher stability;learning converges faster w/llm constaints;actioneff reward cuts unnecessary unpacking | T53: the llm guidance improve space use+stack stability;yielding robust;realtime robotic packing | V53: physicsbased endtoend rl sampleinefficient | W53: Enhance — Generates feasibility and packing/unpacking heuristics to constrain actions and enrich exploration efficiently. Decide — Guides DRL to choose pack vs. unpack and target positions for higher utilization and stability. Act — Executes chosen actions on UR5, performing real packing/unpacking with low-latency control | X53: gpt4generated feasibility/strategy code fused w/action masks | Z53: 4 | AA53: 3 | AB53: Lab validation | AC53: Core function validation | AD53: GenAI-led with human oversight | AE53: N | AF53: Field pilots – Subsystem demonstration in relevant environment Autonomous process learning | AG53: PUSNet is trained in simulation and then deployed via sim2real on a real robot, performing full packing tasks in logistics-like scenarios as an integrated cell, beyond offline benchmarking but short of plant-wide deployment. | AH53: The LLM generates heuristics shaping the DRL policy, which then autonomously decides packing and unpacking actions on the robot without human approval per move; humans supervise safety and setup but are largely out of the loop. | AI53: The study presented in the article involves both simulation experiments and real-world robotic packing tests. The authors first train and evaluate their proposed "packing-and-unpacking synergistic network (PUSNet)" in a virtual environment using various datasets 12. They then deploy the learned synergistic policy on a real UR5 robotic arm equipped with a suction gripper to perform online robotic packing tasks in diverse logistics scenarios 3. The results demonstrate that the PUSNet-based robotic packing system can achieve reliable and space-efficient packing performance in the real world 4. | AK53: {=_xlfn.IFS(AC53="Principles observation",1, AC53="Concept formulation",2, AC53="Proof-of-concept simulation", 3, AC53="Core function validation", 4, AC53="Integration component testing", 5, AC53="Component validation in relevant environment", 6, AC53="Subsystem demonstration in relevant environment", 7, AC53="System demonstration in operational environment", 8, AC53="Production qualification", 9, AC53="Mission-proven operations", 10)} -> 4 | AL53: {=_xlfn.IFS(AD53="Assistive GenAI", 1, AD53="GenAI-led with human oversight", 2, AD53="Autonomous process learning", 3)} -> 2
A54: 58 | B54: Large language models for extrapolative modeling of manufacturing processes | C54: Naghavi Khanghah K.; Patel A.; Malhotra R.; Xu H. | D54: 2025 | E54: Journal of Intelligent Manufacturing | F54: 0 | G54: =IFERROR(LEFT(C54, FIND(";", C54) - 1), C54) -> Naghavi Khanghah K. | H54: School of Mechanical, Aerospace and Manufacturing Engineering, University of Connecticut, Storrs, 06269, CT, United States | I54: Iterative model refinement; Large language model; Manufacturing process modelling; Retrieval-augmented generation | J54: =IF(OR( E54="International Journal of Production Research", E54="Journal of Manufacturing Technology Management", E54="International Journal of Production Economics", E54="Journal of Industrial Information Integration", E54="Transportation Research Part E: Logistics and Transportation Review", E54="Journal of Cleaner Production", E54="MM 2024 - Proceedings of the 32nd ACM International Conference on Multimedia", E54="Oeconomia Copernicana", E54="Technology in Society" ), "MGT", "ENG") -> ENG | K54: empirical | L54: Design science research | M54: Techniques | N54: Manufacturing | O54: Process planning | R54: LLM chatbot | S54: combining literature rag w/iterative llm refinement yields high extrapolative acc w/tiny datasets;rag stabilizes generalization+removes human literature interpretation | T54: genai reduce data needs+improve extrapolation for proc modles;enabling faster;less expertdependent parameterperf prediction across diverse mfg processes | U54: curate related papers | V54: perf depends on retrieved literature qual+presence of closedform equations;ragonly can inaccurate;w/orag refinement may unstable;broader automation of selection left for future work | W54: Enhance — Retrieves and structures literature knowledge into candidate equations and parametric relationships for modeling robust extrapolation. Decide — Generates, fits, ranks, and iteratively refines analytical models using small experiments for extrapolation beyond training. | X54: rag gpt4omini;iterative equation refinement;candidate reranking | Z54: 4 | AA54: 3 | AB54: Lab validation | AC54: Core function validation | AD54: Assistive GenAI | AE54: Y | AG54: The LLM-based framework learns analytical models from literature plus small experimental datasets for three manufacturing processes. All evaluations use curated lab/experimental data offline; no linkage to live equipment, control loops, or plant IT/OT. | AH54: GenAI is used to read literature, propose candidate equations, and refine models; it never controls machines or runs online. Outputs are decision-support models for engineers, keeping humans as ultimate decision-makers and “button pressers.” | AK54: {=_xlfn.IFS(AC54="Principles observation",1, AC54="Concept formulation",2, AC54="Proof-of-concept simulation", 3, AC54="Core function validation", 4, AC54="Integration component testing", 5, AC54="Component validation in relevant environment", 6, AC54="Subsystem demonstration in relevant environment", 7, AC54="System demonstration in operational environment", 8, AC54="Production qualification", 9, AC54="Mission-proven operations", 10)} -> 4 | AL54: {=_xlfn.IFS(AD54="Assistive GenAI", 1, AD54="GenAI-led with human oversight", 2, AD54="Autonomous process learning", 3)} -> 1
A55: 59 | B55: Graph Structure-Enhanced Large Language Model for Optical Network Fault Diagnosis: An Explainable Alarm Root Cause Localization Approach | C55: Wang Y.; Pang Y.; Liu Y.; Zhang Y.; Zhang L.; Zhang M.; Wang D. | D55: 2025 | E55: IEEE Internet of Things Journal | F55: 0 | G55: =IFERROR(LEFT(C55, FIND(";", C55) - 1), C55) -> Wang Y. | H55: Beijing University of Posts and Telecommunications, State Key Laboratory of Information Photonics and Optical Communications, Beijing, 100876, China | I55: Fault Management; Graph Structure; Large Language Models; Optical Network; Root Cause Localization | J55: =IF(OR( E55="International Journal of Production Research", E55="Journal of Manufacturing Technology Management", E55="International Journal of Production Economics", E55="Journal of Industrial Information Integration", E55="Transportation Research Part E: Logistics and Transportation Review", E55="Journal of Cleaner Production", E55="MM 2024 - Proceedings of the 32nd ACM International Conference on Multimedia", E55="Oeconomia Copernicana", E55="Technology in Society" ), "MGT", "ENG") -> ENG | K55: empirical | L55: Design science research | M55: Techniques | N55: Operations | O55: fault diagnosis | P55: Telecommunications | R55: KG‑augmented LLM | S55: graph RCL attains ≥86.8% acc in complex multiroot scenarios;single/double/triplecause accuracies 97.09/89.26/86.84%;fine tunw RCLllm improve acc over base by~8794%+use 501400 fewer tokens per answer;aggregated fine tunning beat separate modles | T55: a fine tunw;kgaugmented llm reduce op learning costs;adds interactivity/explainability,+improve diagnostic reliabilty+speed for alarm floods versus manual or basellm analysis | V55: perf depends on APRA/NTA data qual;error accumulation across steps;acc declines as rootcause count/scene complexity rises;fine tunning/data prep effort | W55: Enhance — Structures topology/propagation knowledge as text modules and explains intermediate reasoning steps. Decide — Localizes root-cause alarms from floods via learned graph-guided chains with verifiable logic. | X55: kgaugmented llm for root cause analysis in optical networks;supervised lora fine tunning of llama38BInstruct using gpt4o teachergenerated CoT data | Z55: 4 | AA55: 3 | AB55: Lab validation | AC55: Core function validation | AD55: Assistive GenAI | AE55: Y | AG55: RCL-LLM is fine-tuned and evaluated on real OTN alarm data and simulated scenarios, achieving high root-cause localization accuracy. However, it runs as an offline diagnostic tool, not integrated into live network operations. | AH55: The system analyzes alarms, explains likely root causes, and reduces operator workload, but it only provides diagnostic insights. Operators still decide and execute recovery actions; GenAI does not directly reconfigure or control the network. | AK55: {=_xlfn.IFS(AC55="Principles observation",1, AC55="Concept formulation",2, AC55="Proof-of-concept simulation", 3, AC55="Core function validation", 4, AC55="Integration component testing", 5, AC55="Component validation in relevant environment", 6, AC55="Subsystem demonstration in relevant environment", 7, AC55="System demonstration in operational environment", 8, AC55="Production qualification", 9, AC55="Mission-proven operations", 10)} -> 4 | AL55: {=_xlfn.IFS(AD55="Assistive GenAI", 1, AD55="GenAI-led with human oversight", 2, AD55="Autonomous process learning", 3)} -> 1
A56: 61 | B56: A large manufacturing decision model for human-centric decision-making | C56: Li X.; Nassehi A., (1); Hu S.J., (1); Joung B.G.; Gao R.X., (1) | D56: 2025 | E56: CIRP Annals | F56: 0 | G56: =IFERROR(LEFT(C56, FIND(";", C56) - 1), C56) -> Li X. | H56: School of Engineering Technology, Purdue University, West Lafayette, United States | I56: Digital twin; Generative artificial intelligence; Manufacturing system | J56: =IF(OR( E56="International Journal of Production Research", E56="Journal of Manufacturing Technology Management", E56="International Journal of Production Economics", E56="Journal of Industrial Information Integration", E56="Transportation Research Part E: Logistics and Transportation Review", E56="Journal of Cleaner Production", E56="MM 2024 - Proceedings of the 32nd ACM International Conference on Multimedia", E56="Oeconomia Copernicana", E56="Technology in Society" ), "MGT", "ENG") -> ENG | K56: empirical | L56: Design science research | M56: Techniques | N56: Manufacturing | Q56: human-centric decision-making | R56: VLM; LLM chatbot | S56: a dtguided diffusion modle gen precise;diverse reconfiguration options w/>80% acc in 9/10 targets+~10 MSE | T56: the Large mfg Decision modle accelerates humancentric reconfiguration;aligning options to perf targets in realtime+reducing risk w/dt vaild;it transforms massive simulaiton/sensor data into actionable decisions w/minimal initial datasets | V56: perf depends on dt fidelity+coverage;generalizability to larger scales/objectives need work;need greater interpretability+tighter integr of llm reasoning in future iterations | W56: Enhance — Learns decision patterns from DT simulations, structuring reconfiguration as matrix images. Decide — Generates target-aligned reconfiguration options, ranking by DT-evaluated performance for human selection. Act — Outputs executable configuration matrices to update resources after DT validation and human approval | X56: uNet diffusion for decision matrices;llm interface for text→target parsing;dtguided selftraining | Y56: not so clear or detailed | Z56: 4 | AA56: 3 | AB56: Concept | AC56: Proof-of-concept simulation | AD56: Assistive GenAI | AE56: Y | AG56: LMDM is implemented on a flexible manufacturing system modeled via discrete-event/digital-twin simulation, generating and evaluating reconfiguration decisions offline, without controlling real assets or being integrated into a plant IT/OT stack. | AH56: The model autonomously proposes multiple reconfiguration options and evaluates them against performance targets, but humans remain central by interpreting options and choosing final decisions; no direct execution on physical equipment is reported. | AK56: {=_xlfn.IFS(AC56="Principles observation",1, AC56="Concept formulation",2, AC56="Proof-of-concept simulation", 3, AC56="Core function validation", 4, AC56="Integration component testing", 5, AC56="Component validation in relevant environment", 6, AC56="Subsystem demonstration in relevant environment", 7, AC56="System demonstration in operational environment", 8, AC56="Production qualification", 9, AC56="Mission-proven operations", 10)} -> 3 | AL56: {=_xlfn.IFS(AD56="Assistive GenAI", 1, AD56="GenAI-led with human oversight", 2, AD56="Autonomous process learning", 3)} -> 1
A57: 62 | B57: From analogy to innovation: A creative conceptual design approach leveraging large language models | C57: Wang B.; Zhao X.; Zuo H.; Song Y.; Han J.; Childs P.; Chen L. | D57: 2025 | E57: Advanced Engineering Informatics | F57: 0 | G57: =IFERROR(LEFT(C57, FIND(";", C57) - 1), C57) -> Wang B. | H57: Dyson School of Design Engineering, Imperial College London, Exhibition Rd, South Kensington, SW7 2AZ, United Kingdom | I57: Analogy; Artificial intelligence; Conceptual product design; Creativity; Innovation; Large language models | J57: =IF(OR( E57="International Journal of Production Research", E57="Journal of Manufacturing Technology Management", E57="International Journal of Production Economics", E57="Journal of Industrial Information Integration", E57="Transportation Research Part E: Logistics and Transportation Review", E57="Journal of Cleaner Production", E57="MM 2024 - Proceedings of the 32nd ACM International Conference on Multimedia", E57="Oeconomia Copernicana", E57="Technology in Society" ), "MGT", "ENG") -> ENG | K57: empirical | L57: Design science research | M57: Techniques | N57: Design | O57: Generative design | P57: Consumer products | Q57: Design-by-analogy | R57: LLM chatbot | S57: zeroshot llm analogy+scoring+combination lifted creativity:expertrated novelty+51%;functionality+22%;analogy eff/diversity+≈30%;designers reported lower mental/physical demand | T57: interactive ViMimic tool using gpt4o zeroshot accelerates ideation;expands analogy diversity,+reduce cognitive load;helping designers move from analogies to viable concepts more systematically | V57: blackbox risks remain despite scoring;generalization beyond case scope needs work | W57: Enhance — Structures problem/solution spaces and retrieves far-semantic, near-morphology analogies for designers. Decide — Synthesizes analogical features into coherent concept options with inspirations and explanations. | X57: llmdriven pipeline w/Primitives Scheme Block → Analogy Mapping → Scoring semantic+shape distances → Combination | Z57: 4 | AA57: 3 | AB57: Lab validation | AC57: Core function validation | AD57: Assistive GenAI | AE57: Y | AG57: The ViMimic tool is a working software prototype tested with 18 participants on realistic conceptual design tasks, demonstrating improved novelty and functionality, but it remains a lab PDMS add-on, not integrated into industrial workflows. | AH57: The LLM retrieves analogies, scores mappings, and suggests combinational concepts, while designers judge relevance, adapt ideas, and make all design decisions; the system does not act on production or engineering processes directly. | AK57: {=_xlfn.IFS(AC57="Principles observation",1, AC57="Concept formulation",2, AC57="Proof-of-concept simulation", 3, AC57="Core function validation", 4, AC57="Integration component testing", 5, AC57="Component validation in relevant environment", 6, AC57="Subsystem demonstration in relevant environment", 7, AC57="System demonstration in operational environment", 8, AC57="Production qualification", 9, AC57="Mission-proven operations", 10)} -> 4 | AL57: {=_xlfn.IFS(AD57="Assistive GenAI", 1, AD57="GenAI-led with human oversight", 2, AD57="Autonomous process learning", 3)} -> 1
A58: 63 | B58: MASC: Large language model-based multi-agent scheduling chain for flexible job shop scheduling problem | C58: Wang Z.; Wan C.; Liu J.; Zhang X.; Wang H.; Hu Y.; Hu Z. | D58: 2025 | E58: Advanced Engineering Informatics | F58: 0 | G58: =IFERROR(LEFT(C58, FIND(";", C58) - 1), C58) -> Wang Z. | H58: School of Mechanical Science and Engineering, Huazhong University of Science and Technology, Wuhan, 430074, China | I58: Flexible job shop scheduling; Intelligent manufacturing; Large language model; Multi-agent systems | J58: =IF(OR( E58="International Journal of Production Research", E58="Journal of Manufacturing Technology Management", E58="International Journal of Production Economics", E58="Journal of Industrial Information Integration", E58="Transportation Research Part E: Logistics and Transportation Review", E58="Journal of Cleaner Production", E58="MM 2024 - Proceedings of the 32nd ACM International Conference on Multimedia", E58="Oeconomia Copernicana", E58="Technology in Society" ), "MGT", "ENG") -> ENG | K58: empirical | L58: Design science research | M58: Techniques | N58: Operations | O58: Scheduling | R58: LLM agents | S58: llm multiagent sys for realtime rescheduling succeeds for machine failure+urgent orders | T58: a Multiagent scheduling chain fw improve scheduling eff+adaptability;enabling NL requests;quick algorithm selection,+nearrealtime rescheduling w/reduced manual intervention across dynamic shop conditions | V58: inference latency~20 s avg;hardwaredependent;perf varies by dataset/scene complexity;risk of knowlege forgetting w/o DialBag | W58: Enhance — Extracts case indicators and standardizes semantic requests to enrich decision context. Decide — Chooses and runs suitable schedulers (GA/MIP/rules) and reschedules under disruptions. Act — Converts plans to robot control commands via Plan/Ctrl agents for execution. | X58: multiagent scheduling chain fw:InternLM27B Qlora;improved ReAct;DialBag | Z58: 4 | AA58: 3 | AB58: Lab validation | AC58: Integration component testing | AD58: GenAI-led with human oversight | AE58: Y | AG58: MASC is realized as a multi-agent system connected to robots and control software, validated via simulations and real robotic experiments in a research testbed, but not deployed on a live production line or plant MES. | AH58: SchedAgent, PlanAgent and CtrlAgent jointly generate schedules, translate them into commands and directly control robotic equipment, adapting to disturbances, while humans define objectives, constraints and monitor behavior rather than micromanaging each scheduling decision. | AK58: {=_xlfn.IFS(AC58="Principles observation",1, AC58="Concept formulation",2, AC58="Proof-of-concept simulation", 3, AC58="Core function validation", 4, AC58="Integration component testing", 5, AC58="Component validation in relevant environment", 6, AC58="Subsystem demonstration in relevant environment", 7, AC58="System demonstration in operational environment", 8, AC58="Production qualification", 9, AC58="Mission-proven operations", 10)} -> 5 | AL58: {=_xlfn.IFS(AD58="Assistive GenAI", 1, AD58="GenAI-led with human oversight", 2, AD58="Autonomous process learning", 3)} -> 2
A59: 64 | B59: Probing a novel machine tool fault reasoning and maintenance service recommendation approach through data-knowledge empowered LLMs integrated with AR-assisted maintenance guidance | C59: Liu C.; Song J.; Tang D.; Wang L.; Zhu H.; Cai Q. | D59: 2025 | E59: Advanced Engineering Informatics | F59: 0 | G59: =IFERROR(LEFT(C59, FIND(";", C59) - 1), C59) -> Liu C. | H59: College of Mechanical and Electrical Engineering, Nanjing University of Aeronautics and Astronautics, Nanjing, 210016, China | I59: Augmented reality; data-knowledge empowered LLMs; Fault reasoning; Machine tools; Maintenance service recommendation | J59: =IF(OR( E59="International Journal of Production Research", E59="Journal of Manufacturing Technology Management", E59="International Journal of Production Economics", E59="Journal of Industrial Information Integration", E59="Transportation Research Part E: Logistics and Transportation Review", E59="Journal of Cleaner Production", E59="MM 2024 - Proceedings of the 32nd ACM International Conference on Multimedia", E59="Oeconomia Copernicana", E59="Technology in Society" ), "MGT", "ENG") -> ENG | K59: empirical | L59: Design science research | M59: Techniques | N59: Operations | O59: fault diagnosis; maintenance | P59: Machinery | R59: LLM agents | S59: scenegraphenhanced;prompttuned llm improve fault reasoning+maint recs across multifault scenarios+cuts maint time | T59: multiagent llm raises diagnostic acc/robustness+reduce downtime by delivering precise;explainable recs+ondevice ar guidance for technicians | U59: curated scene graph entities/relations/attributes fused w/shopfloor sys;data preprocessing 3σ+Isolation Forest;Bayesian multiimputation;synthetic multifault augmentation | V59: perf depends on scenegraph qual+sys integr;latency/compute+device limits ;HoloLens battery/heat;noisy environments must managed | W59: Enhance — Aligns unstructured fault/maintenance knowledge via scene-graph RAG for richer context. Decide — Reasons about root causes and ranks maintenance services through multi-agent, prompt-tuned LLM. Act — Triggers work orders and overlays stepwise AR guidance for on-site execution. | X59: build fault & maint scene graph fault IDs;phenomena;locations;causes | Y59: LLM-enabled scene-graph RAG (GraphRAG+Neo4j) with prompt-tuned multi-agent LLM for fault diagnosis; compare fault-reasoning & recommendation accuracy vs Gemini/Claude/Llama/GPT-4 | Z59: 4 | AA59: 3 | AB59: Field pilots | AC59: Component validation in relevant environment | AD59: Assistive GenAI | AE59: Y | AG59: The industrial LLM and AR system are deployed in a typical machining workshop with real CNC machine tools, sensors, and HoloLens, using live operational data to diagnose faults and guide maintenance while operators execute tasks on real equipment. | AH59: The system performs fault reasoning, recommends maintenance services, creates work instructions, and overlays AR guidance, but human technicians decide whether to follow suggestions and physically perform interventions; no autonomous actuation of machine tools is described. | AK59: {=_xlfn.IFS(AC59="Principles observation",1, AC59="Concept formulation",2, AC59="Proof-of-concept simulation", 3, AC59="Core function validation", 4, AC59="Integration component testing", 5, AC59="Component validation in relevant environment", 6, AC59="Subsystem demonstration in relevant environment", 7, AC59="System demonstration in operational environment", 8, AC59="Production qualification", 9, AC59="Mission-proven operations", 10)} -> 6 | AL59: {=_xlfn.IFS(AD59="Assistive GenAI", 1, AD59="GenAI-led with human oversight", 2, AD59="Autonomous process learning", 3)} -> 1
A60: 65 | B60: Customization and personalization of large language models for engineering design | C60: Jiang Z.; Liu A.; Zhang D.; Xu X.; Dai Y. | D60: 2025 | E60: CIRP Annals | F60: 0 | G60: =IFERROR(LEFT(C60, FIND(";", C60) - 1), C60) -> Jiang Z. | H60: The Southern University of Science and Technology, Guangdong, Shenzhen, 518055, China | I60: Artificial intelligence; engineering design; large language model | J60: =IF(OR( E60="International Journal of Production Research", E60="Journal of Manufacturing Technology Management", E60="International Journal of Production Economics", E60="Journal of Industrial Information Integration", E60="Transportation Research Part E: Logistics and Transportation Review", E60="Journal of Cleaner Production", E60="MM 2024 - Proceedings of the 32nd ACM International Conference on Multimedia", E60="Oeconomia Copernicana", E60="Technology in Society" ), "MGT", "ENG") -> ENG | K60: empirical | L60: Design science research | M60: Techniques | N60: Design | O60: Generative design | R60: LLM chatbot | S60: customizing w/patentrag+personalizing w/designreasoning prompts improve concept feasibility+usefulness versus general llm;novelty may decrease after customization;w/partial recovery w/personalization;adapted modles stabilize qual compared to higher variance in general llm outputs | T60: ragcustomized llm designspecific+personalized prompting makes conceptual design more manufacturable+contextrelevant;reduce hallucinations/outdated knowlege w/justintime retrieval,+better suport designers in early concept work | U60: large patent corpus ingestion | V60: dependence on data qual/coverage | W60: Enhance — Retrieves and structures patent knowledge into prompts to ground concept generation. Decide — Synthesizes concepts by reasoning with constraints/analogies, trading novelty for feasible, manufacturable ideas | X60: ragcustomized llm designspecific+personalized prompting reasoningguided CoT/ToT;gpt4o baseline | Y60: conceptual design ideation from patents | Z60: 4 | AA60: 3 | AB60: Concept | AC60: Proof-of-concept simulation | AD60: Assistive GenAI | AE60: Y | AG60: The paper mainly proposes customization and personalization frameworks and validates them via a controlled conceptual design experiment using patents and LLM-based RAG; it is not embedded into industrial CAD/PLM or operational manufacturing systems. | AH60: Customized and personalized LLMs generate concept alternatives and reasoning traces; human designers and experts evaluate feasibility and novelty, and any downstream engineering or manufacturing actions remain fully human-initiated. | AK60: {=_xlfn.IFS(AC60="Principles observation",1, AC60="Concept formulation",2, AC60="Proof-of-concept simulation", 3, AC60="Core function validation", 4, AC60="Integration component testing", 5, AC60="Component validation in relevant environment", 6, AC60="Subsystem demonstration in relevant environment", 7, AC60="System demonstration in operational environment", 8, AC60="Production qualification", 9, AC60="Mission-proven operations", 10)} -> 3 | AL60: {=_xlfn.IFS(AD60="Assistive GenAI", 1, AD60="GenAI-led with human oversight", 2, AD60="Autonomous process learning", 3)} -> 1
A61: 66 | B61: Conceptualisation of a multimodal, non-intrusive, generative AI-based assistive system for assembly | C61: Simeone A.; Fan Y.; Antonelli D.; Priarone P.C.; Settineri L. | D61: 2025 | E61: CIRP Annals | F61: 0 | G61: =IFERROR(LEFT(C61, FIND(";", C61) - 1), C61) -> Simeone A. | H61: Department of Management and Production Engineering, Politecnico di Torino, Corso Duca degli Abruzzi 24, Torino, 10129, Italy | I61: Assembly; Generative artificial intelligence; Multimodal assistance | J61: =IF(OR( E61="International Journal of Production Research", E61="Journal of Manufacturing Technology Management", E61="International Journal of Production Economics", E61="Journal of Industrial Information Integration", E61="Transportation Research Part E: Logistics and Transportation Review", E61="Journal of Cleaner Production", E61="MM 2024 - Proceedings of the 32nd ACM International Conference on Multimedia", E61="Oeconomia Copernicana", E61="Technology in Society" ), "MGT", "ENG") -> ENG | K61: empirical | L61: Design science research | M61: Applications | N61: Manufacturing | O61: fault diagnosis; maintenance | P61: Machinery | Q61: Industry 5.0 human-centric | R61: LLM chatbot | S61: chatgpt achieved 84% firstattempt success in error detection no false negatives;16% false positives+84% firstattempt acc in descrips/corrections;op feedback prompts fixed remaining cases to 100%;warnings mitigated 11/12 critical steps | T61: multimodal llm assistant chatgpt v4.0;claude 3.5 enable realtime;nonintrusive guidance;reduce assembly errors | U61: python API integr;feedback learning storing op corrections to update prompts+modality priorities | V61: latency vs stateofart DL detectors;reliance on prompt design;labscale vaild;generic genai not yet optimised for industrial use | W61: Enhance — Structures multimodal scene and operator profiles, producing tailored prompts, warnings, and updated corrective knowledge records. Decide — Detects assembly errors, selects assistive modality, and prioritizes guidance using reference comparisons and context analysis. Act — Generates instructions and executes device commands: project visuals, play audio, trigger robot interventions when necessary. | X61: no fine tunning | Z61: 4 | AA61: 3 | AB61: Lab validation | AC61: Integration component testing | AD61: GenAI-led with human oversight | AE61: Y | AG61: Laboratory assembly cell combines cameras, LLMs, projector, audio, databases and cobot to deliver warnings and corrective guidance on pump assembly, but authors emphasise preliminary lab-scale results without factory integration yet. | AH61: GenAI layer interprets images, detects assembly errors, selects assistive modality, and commands cobot for item handling; human operators execute main tasks, provide feedback, and can override or correct system behaviour. | AK61: {=_xlfn.IFS(AC61="Principles observation",1, AC61="Concept formulation",2, AC61="Proof-of-concept simulation", 3, AC61="Core function validation", 4, AC61="Integration component testing", 5, AC61="Component validation in relevant environment", 6, AC61="Subsystem demonstration in relevant environment", 7, AC61="System demonstration in operational environment", 8, AC61="Production qualification", 9, AC61="Mission-proven operations", 10)} -> 5 | AL61: {=_xlfn.IFS(AD61="Assistive GenAI", 1, AD61="GenAI-led with human oversight", 2, AD61="Autonomous process learning", 3)} -> 2
A62: 67 | B62: Large language model-driven multi-agent systems for improving production efficiency and reducing carbon emissions in manufacturing | C62: Wu T.; Li J.; Bao J.; Liu Q. | D62: 2025 | E62: Computers and Industrial Engineering | F62: 0 | G62: =IFERROR(LEFT(C62, FIND(";", C62) - 1), C62) -> Wu T. | H62: College of Mechanical Engineering, Donghua University, Shanghai, 201620, China | I62: Autonomous Agent; Carbon Emission Management; Customized Production; Digital Twin; Large Language Model; Multi-Agent Systems | J62: =IF(OR( E62="International Journal of Production Research", E62="Journal of Manufacturing Technology Management", E62="International Journal of Production Economics", E62="Journal of Industrial Information Integration", E62="Transportation Research Part E: Logistics and Transportation Review", E62="Journal of Cleaner Production", E62="MM 2024 - Proceedings of the 32nd ACM International Conference on Multimedia", E62="Oeconomia Copernicana", E62="Technology in Society" ), "MGT", "ENG") -> ENG | K62: empirical | L62: Design science research | M62: Techniques | N62: Operations | O62: Scheduling | P62: Textile | R62: LLM enabled digital twin; LLM agents | S62: the llmenhanced dtMultiAgent sys reduce tardiness;balances workloads,+lowers carbon emissions versus rules;metaheuristics,+plain rl | T62: llmenhanced dtMultiAgent sys improve scheduling eff+carbon mitigation;supports fast rescheduling under machine failures/urgent orders,+cuts execution time compared w/GA/GP+baseline | U62: llm fine tunning on domian corpus | V62: effectiveness depends on eventlog/DFG qual+domian KB coverage;integr/compute cost for llm fine tunning;generalization beyond case+weightsetting robustness need further | W62: Enhance — Transforms event logs into semantic process knowledge and infers objective weights from intents for scheduling. Decide — Guides negotiation and multi-objective scheduling, selecting machine combinations and quantities under constraints and uncertainties adaptively. Act — Issues task allocations to machines via DT agents and updates schedules for execution in realtime | X62: dt;DFG mining;Vicuna13B fine tunning;PPO rl | Z62: 4 | AA62: 3 | AB62: Lab validation | AC62: Core function validation | AD62: GenAI-led with human oversight | AE62: Y | AG62: Implements CarbonDTMAS using real production data from a textile workshop; evaluates multi-objective scheduling performance against baselines in a case study, but system remains offline without direct integration into live plant control. | AH62: LLM-enhanced multi-agents autonomously propose schedules optimizing tardiness, workload and emissions inside the DT; humans supervise, interpret results, and enact plans, so GenAI does not directly operate equipment. | AK62: {=_xlfn.IFS(AC62="Principles observation",1, AC62="Concept formulation",2, AC62="Proof-of-concept simulation", 3, AC62="Core function validation", 4, AC62="Integration component testing", 5, AC62="Component validation in relevant environment", 6, AC62="Subsystem demonstration in relevant environment", 7, AC62="System demonstration in operational environment", 8, AC62="Production qualification", 9, AC62="Mission-proven operations", 10)} -> 4 | AL62: {=_xlfn.IFS(AD62="Assistive GenAI", 1, AD62="GenAI-led with human oversight", 2, AD62="Autonomous process learning", 3)} -> 2
A63: 68 | B63: Large language model-enabled multi-agent self-organised approach for personalised rehabilitation assistive devices design | C63: Zhuang W.; Pan X.; Wen S.; Yu W.; Li X.; Bao J. | D63: 2025 | E63: International Journal of Production Research | F63: 0 | G63: =IFERROR(LEFT(C63, FIND(";", C63) - 1), C63) -> Zhuang W. | H63: College of Mechanical Engineering, Donghua University, Shanghai, 201620, China | I63: large language model; multi-agent system; personalised product design; Rehabilitation assistive devices; self-organisation | J63: ENG | K63: empirical | L63: Design science research | M63: Techniques | N63: Design | O63: Generative design | P63: Medical devices | R63: LLM enabled KG; KG‑augmented LLM; LLM agents | S63: the llmPDAgents fw use kg+multiagent workflow to plan roles/steps;gen+refine personalised RAD designs,+;on kneeRAD case;improve procedure+design qual | T63: better personalisation+manufacturability w/fewer iterations;more transparent reasoning kgguided CoT,+lower design effort/cost compared w/adhoc manual methods | U63: real data 1000 kneeRAD entries from Amazon/Taobao/Soopat to ground kg | V63: domian data scarcity;reliance on kg qual;risk of agent loops human expert fallback after threshold,+generalisation beyond kneeRADs;limitd pretraining resorces in medicalrehab domian | W63: Enhance — Builds KG and evidence graphs to align user needs with design knowledge and constraints effectively. Decide — Plans steps, defines expert roles, and composes/refines personalized RAD design proposals via reasoning and feedback. Act — Generates detailed design outputs, material/process choices, and orchestrates collaboration patterns for execution and documentation handoff. | X63: fbsbased kg;multiagent planing | Z63: 4 | AA63: 4 | AB63: Lab validation | AC63: Core function validation | AD63: GenAI-led with human oversight | AE63: Y | AG63: Implements LLM-based multi-agent plus knowledge graph, runs a full knee joint rehabilitation-device design case, 3D-prints and evaluates prototypes, but workflow remains a research prototype rather than embedded industrial design toolchain. | AH63: System captures user requirements, plans tasks and iteratively generates design proposals, yet expert designers and end users review, modify, and ultimately approve designs, keeping GenAI as planner under human oversight. | AK63: {=_xlfn.IFS(AC63="Principles observation",1, AC63="Concept formulation",2, AC63="Proof-of-concept simulation", 3, AC63="Core function validation", 4, AC63="Integration component testing", 5, AC63="Component validation in relevant environment", 6, AC63="Subsystem demonstration in relevant environment", 7, AC63="System demonstration in operational environment", 8, AC63="Production qualification", 9, AC63="Mission-proven operations", 10)} -> 4 | AL63: {=_xlfn.IFS(AD63="Assistive GenAI", 1, AD63="GenAI-led with human oversight", 2, AD63="Autonomous process learning", 3)} -> 2
A64: 70 | B64: Generative AI meets CAD: enhancing engineering design to manufacturing processes with large language models | C64: Daareyni A.; Martikkala A.; Mokhtarian H.; Ituarte I.F. | D64: 2025 | E64: International Journal of Advanced Manufacturing Technology | F64: 0 | G64: =IFERROR(LEFT(C64, FIND(";", C64) - 1), C64) -> Daareyni A. | H64: Faculty of Engineering and Natural Sciences, Tampere University, Korkeakoulunkatu 6, Pirkanmaa, Tampere, 33014, Finland | I64: Artificial intelligence; Chat-GPT; Computer-aided design; Design automation; Large language models | J64: =IF(OR( E64="International Journal of Production Research", E64="Journal of Manufacturing Technology Management", E64="International Journal of Production Economics", E64="Journal of Industrial Information Integration", E64="Transportation Research Part E: Logistics and Transportation Review", E64="Journal of Cleaner Production", E64="MM 2024 - Proceedings of the 32nd ACM International Conference on Multimedia", E64="Oeconomia Copernicana", E64="Technology in Society" ), "MGT", "ENG") -> ENG | K64: empirical | L64: Design science research | M64: Techniques | N64: Design | O64: Generative design | R64: LLM chatbot | S64: the fw turns text/images/voice into CAD code+;w/closed loop checks;refines modles to match user specs;imageonly inputs capture general form but miss precise dimensions | T64: lowers CAD barriers;speeds rapid prototyping,+links design→mfg STL/Gcode/printing in one workflow for nonexperts+engineers | U64: structured prompts JSON+library injection | V64: llms dont handle 3D natively;dimensional acc suffers w/o explicit specs;execution time/cost issues for alternative/commercial modles;complex geometries+robust scaling remain open | W64: Enhance — Converts multimodal inputs into OpenSCAD code; self-evaluates via projections, refining syntax, geometry, and dimensions iteratively. Decide — Generates and revises CAD scripts toward user specifications, selecting libraries and parameters during iterations automatically. Act — Outputs STL and G-code; triggers 3D printing and updates models after syntax checks and validation | X64: gpt4o prompts;OpenSCAD;Streamlit UI | Z64: 4 | AA64: 3 | AB64: Lab validation | AC64: Integration component testing | AD64: Assistive GenAI | AE64: Y | AG64: Pipeline connects GPT-4, OpenSCAD scripts, slicer and desktop 3D printer, tested on gear-case examples with dimensional error analysis, demonstrating an integrated workflow only in a controlled laboratory environment. | AH64: GenAI produces CAD and G-code alternatives from prompts; users inspect geometry, adjust parameters and explicitly trigger printing, so the model serves as creative copilot rather than independently controlling fabrication hardware. | AI64: core function of generating CAD design | AK64: {=_xlfn.IFS(AC64="Principles observation",1, AC64="Concept formulation",2, AC64="Proof-of-concept simulation", 3, AC64="Core function validation", 4, AC64="Integration component testing", 5, AC64="Component validation in relevant environment", 6, AC64="Subsystem demonstration in relevant environment", 7, AC64="System demonstration in operational environment", 8, AC64="Production qualification", 9, AC64="Mission-proven operations", 10)} -> 5 | AL64: {=_xlfn.IFS(AD64="Assistive GenAI", 1, AD64="GenAI-led with human oversight", 2, AD64="Autonomous process learning", 3)} -> 1
